Workbook

Sheet PRISMA Dashboard
A1: IDENTIFICATION
A2: Records identified (databases) | B2: 793
A3: Scopus / IEEE / arXiv | B3: 451 / 237 / 105
A4: Duplicates removed before screening | B4: 241
A5: automated (216) + manual (25) | B5: 216 + 25
A7: SCREENING (Stage 1: title/abstract)
A8: Records screened | B8: =COUNTA(Screening!B2:B548) -> 547
A9: Included | B9: =COUNTIF(Screening!G2:G548,"Include") -> 203
A10: Maybe (carry forward) | B10: =COUNTIF(Screening!G2:G548,"Maybe") -> 67
A11: Excluded | B11: =COUNTIF(Screening!G2:G548,"Exclude") -> 277
A12: Not yet screened | B12: =COUNTA(Screening!B2:B548)-COUNTA(Screening!G2:G548) -> 0
A13: Reports sought for retrieval (Include+Maybe) | B13: =COUNTIF(Screening!G2:G548,"Include")+COUNTIF(Screening!G2:G548,"Maybe") -> 270
A15: Stage 1 exclusions by reason
A16: EC1 | B16: =COUNTIFS(Screening!G2:G548,"Exclude",Screening!H2:H548,"EC1") -> 0
A17: EC2 | B17: =COUNTIFS(Screening!G2:G548,"Exclude",Screening!H2:H548,"EC2") -> 0
A18: EC3 | B18: =COUNTIFS(Screening!G2:G548,"Exclude",Screening!H2:H548,"EC3") -> 42
A19: EC4 | B19: =COUNTIFS(Screening!G2:G548,"Exclude",Screening!H2:H548,"EC4") -> 138
A20: EC5 | B20: =COUNTIFS(Screening!G2:G548,"Exclude",Screening!H2:H548,"EC5") -> 36
A21: EC6 | B21: =COUNTIFS(Screening!G2:G548,"Exclude",Screening!H2:H548,"EC6") -> 10
A22: EC7 | B22: =COUNTIFS(Screening!G1:G547,"Exclude",Screening!H1:H547,"EC7") -> 51
A23: EC8 | B23: =COUNTIFS(Screening!G2:G548,"Exclude",Screening!H2:H548,"EC7") -> 51
A26: ELIGIBILITY (Stage 2: full text)
A27: Reports assessed for eligibility | B27: =COUNTA(Screening!I2:I548) -> 76
A28: Excluded (full text) | B28: =COUNTIF(Screening!I2:I548,"Exclude") -> 69
A29: Studies INCLUDED in review | B29: =COUNTIF(Screening!I2:I548,"Include") -> 6
A30: Total Remaining | B30: =B13-B27 -> 194
A31: Total in WIP List [Zotero] | B31: =B30+B29 -> 200
A33: Stage 2 exclusions by reason
A34: EC1 | B34: =COUNTIFS(Screening!I2:I548,"Exclude",Screening!J2:J548,"EC1") -> 1
A35: EC2 | B35: =COUNTIFS(Screening!I2:I548,"Exclude",Screening!J2:J548,"EC2") -> 0
A36: EC3 | B36: =COUNTIFS(Screening!I2:I548,"Exclude",Screening!J2:J548,"EC3") -> 3
A37: EC4 | B37: =COUNTIFS(Screening!I2:I548,"Exclude",Screening!J2:J548,"EC4") -> 3
A38: EC5 | B38: =COUNTIFS(Screening!I2:I548,"Exclude",Screening!J2:J548,"EC5") -> 0
A39: EC6 | B39: =COUNTIFS(Screening!I2:I548,"Exclude",Screening!J2:J548,"EC6") -> 0
A40: EC7 | B40: =COUNTIFS(Screening!I3:I549,"Exclude",Screening!J3:J549,"EC7") -> 7
A41: EC8 | B41: =COUNTIFS(Screening!I4:I550,"Exclude",Screening!J4:J550,"EC8") -> 54

Sheet Screening
A1: # | B1: Title | C1: Authors | D1: Venue | E1: Type | F1: DOI | G1: Stage1 Decision | H1: Stage1 Reason | I1: Stage2 Decision | J1: Stage2 Reason | K1: Abstract | L1: Application domain | M1: Notes | N1: URL
A2: 1 | B2: Quantum-Enhanced Water Quality Monitoring: Exploiting Phi-Sat-2 Data With Quanvolution | C2: F. Mauro; F. Razzano; P. D. Stasio; A. Sebastianelli; G. Meoni; G. Schirinzi; P. Gamba; S. L. Ullo | D2: IEEE (corrupted source record - verify DOI/year) | E2: article | G2: Exclude | H2: EC4 | K2: Coastal water quality monitoring is crucial for environmental sustainability and public health. This work introduces a very cutting-edge methodology, using Φ Sat-2 multispectral data and quanvolutional neural networks (QNNs) to explore quantum-enhanced machine learning (ML) for water contaminant assessment. By integrating quantum preprocessing into a classical regression model, it is possible to achieve a significant reduction in model parameters while maintaining high predictive accuracy. In addition, this work introduces an innovative dataset that integrates simulated Φ Sat-2 spectral data with Copernicus Marine Service biogeochemical products, ensuring a strong alignment between satellite observations and reference turbidity measurements. Our results show that quantum models use up to 98% fewer parameters than their classical counterparts, while achieving a 6.9% improvement in the Pearson correlation coefficient between the Φ Sat-2 preprocessed bands and the ground-truth turbidity values, compared with the case without quantum preprocessing. In addition, the root mean square error (RMSE) improves by 7.3% over the classical baseline. These findings highlight the potential of quantum-assisted remote sensing (RS) to enable more efficient and scalable analysis of large-scale water contaminant data, paving the way for advanced big data approaches in water quality monitoring.
A3: 2 | B3: Absence of Barren Plateaus in Quantum Convolutional Neural Networks | C3: Arthur Pesah and M Cerezo and Samson Wang and Tyler Volkoff and Andrew T Sornborger and Patrick J Coles | D3: Phys. Rev. X 11, 041011 (2021) | E3: article | F3: 10.1103/PhysRevX.11.041011 | G3: Exclude | H3: EC5 | K3: Quantum neural networks (QNNs) have generated excitement around the possibility of efficiently analyzing quantum data. But this excitement has been tempered by the existence of exponentially vanishing gradients, known as barren plateau landscapes, for many QNN architectures. Recently, Quantum Convolutional Neural Networks (QCNNs) have been proposed, involving a sequence of convolutional and pooling layers that reduce the number of qubits while preserving information about relevant data features. In this work we rigorously analyze the gradient scaling for the parameters in the QCNN architecture. We find that the variance of the gradient vanishes no faster than polynomially, implying that QCNNs do not exhibit barren plateaus. This provides an analytical guarantee for the trainability of randomly initialized QCNNs, which highlights QCNNs as being trainable under random initialization unlike many other QNN architectures. To derive our results we introduce a novel graph-based method to analyze expectation values over Haar-distributed unitaries, which will likely be useful in other contexts. Finally, we perform numerical simulations to verify our analytical results. | N3: http://arxiv.org/abs/2011.02966v2
A4: 3 | B4: Hybrid Quantum-Classical Graph Convolutional Network | C4: Samuel Yen-Chi Chen and Tzu-Chieh Wei and Chao Zhang and Haiwang Yu and Shinjae Yoo | E4: misc | G4: Exclude | H4: EC4 | K4: The high energy physics (HEP) community has a long history of dealing with large-scale datasets. To manage such voluminous data, classical machine learning and deep learning techniques have been employed to accelerate physics discovery. Recent advances in quantum machine learning (QML) have indicated the potential of applying these techniques in HEP. However, there are only limited results in QML applications currently available. In particular, the challenge of processing sparse data, common in HEP datasets, has not been extensively studied in QML models. This research provides a hybrid quantum-classical graph convolutional network (QGCNN) for learning HEP data. The proposed framework demonstrates an advantage over classical multilayer perceptron and convolutional neural networks in the aspect of number of parameters. Moreover, in terms of testing accuracy, the QGCNN shows comparable performance to a quantum convolutional neural network on the same HEP dataset while requiring less than $50\%$ of the parameters. Based on numerical simulation results, studying the application of graph convolutional operations and other QML models may prove promising in advancing HEP research and other scientific fields. | N4: http://arxiv.org/abs/2101.06189v1
A5: 4 | B5: Analyzing the barren plateau phenomenon in training quantum neural networks with the ZX-calculus | C5: Chen Zhao and Xiao-Shan Gao | D5: Quantum 5, 466 (2021) | E5: article | F5: 10.22331/q-2021-06-04-466 | G5: Exclude | H5: EC4 | K5: In this paper, we propose a general scheme to analyze the gradient vanishing phenomenon, also known as the barren plateau phenomenon, in training quantum neural networks with the ZX-calculus. More precisely, we extend the barren plateaus theorem from unitary 2-design circuits to any parameterized quantum circuits under certain reasonable assumptions. The main technical contribution of this paper is representing certain integrations as ZX-diagrams and computing them with the ZX-calculus. The method is used to analyze four concrete quantum neural networks with different structures. It is shown that, for the hardware efficient ansatz and the MPS-inspired ansatz, there exist barren plateaus, while for the QCNN ansatz and the tree tensor network ansatz, there exists no barren plateau. | N5: http://arxiv.org/abs/2102.01828v2
A6: 318 | B6: (Formula presented): Exploration of Quantum Deep Learning on Humanities Data from the Perspective of Digital Humanities | C6: Tao Fan and Hao Wang and Tobias Hodel | D6: Social Science Computer Review | E6: article | F6: 10.1177/08944393261416783 | G6: Maybe | H6: Verify QCNN usage and results | I6: Exclude | J6: EC8 | K6: The emergence and advancement of new technologies present promising opportunities for data-driven research in the Digital Humanities (DH). As an innovative intersection of quantum computing and humanities data, Quantum Humanities (QH) holds significant research potential. However, current studies related to QH remain scarce with limited applications involving quantum deep learning, and its feasibility, effectiveness, and efficiency on humanities data need in-depth exploration. To address this gap, this paper takes the role type recognition of painted faces of Beijing Opera as a case study. Several classical and competitive quantum deep learning–based and classical deep learning–based models (e.g., quantum convolutional neural networks and classical convolutional neural networks) are selected for comparison on the public image dataset Painted Faces of Beijing Opera digitized from books. Extensive empirical experimental results demonstrate that quantum deep learning–based models are of certain advantages and hold promising prospects in applied DH practices. © The Author(s) 2026
A7: 13 | B7: 3D Scalable Quantum Convolutional Neural Networks for Point Cloud Data Processing in Classification Applications | C7: Hankyul Baek and Won Joon Yun and Joongheon Kim | E7: misc | G7: Include | H7: QCNN Variant with a use-case/application domain (Point Cloud Data Processing) | I7: Include | J7: Passed by Mahmoud | K7: With the beginning of the noisy intermediate-scale quantum (NISQ) era, a quantum neural network (QNN) has recently emerged as a solution for several specific problems that classical neural networks cannot solve. Moreover, a quantum convolutional neural network (QCNN) is the quantum-version of CNN because it can process high-dimensional vector inputs in contrast to QNN. However, due to the nature of quantum computing, it is difficult to scale up the QCNN to extract a sufficient number of features due to barren plateaus. Motivated by this, a novel 3D scalable QCNN (sQCNN-3D) is proposed for point cloud data processing in classification applications. Furthermore, reverse fidelity training (RF-Train) is additionally considered on top of sQCNN-3D for diversifying features with a limited number of qubits using the fidelity of quantum computing. Our data-intensive performance evaluation verifies that the proposed algorithm achieves desired performance. | N7: http://arxiv.org/abs/2210.09728v1
A8: 7 | B8: Variational Quanvolutional Neural Networks with enhanced image encoding | C8: Denny Mattern and Darya Martyniuk and Henri Willems and Fabian Bergmann and Adrian Paschke | E8: misc | G8: Exclude | H8: EC4 | K8: Image classification is an important task in various machine learning applications. In recent years, a number of classification methods based on quantum machine learning and different quantum image encoding techniques have been proposed. In this paper, we study the effect of three different quantum image encoding approaches on the performance of a convolution-inspired hybrid quantum-classical image classification algorithm called quanvolutional neural network (QNN). We furthermore examine the effect of variational - i.e. trainable - quantum circuits on the classification results. Our experiments indicate that some image encodings are better suited for variational circuits. However, our experiments show as well that there is not one best image encoding, but that the choice of the encoding depends on the specific constraints of the application. | N8: http://arxiv.org/abs/2106.07327v2
A9: 8 | B9: Generalization in quantum machine learning from few training data | C9: Matthias C Caro and Hsin-Yuan Huang and M Cerezo and Kunal Sharma and Andrew Sornborger and Lukasz Cincio and Patrick J Coles | D9: Nat Commun 13, 4919 (2022) | E9: article | F9: 10.1038/s41467-022-32550-3 | G9: Exclude | H9: EC5 | K9: Modern quantum machine learning (QML) methods involve variationally optimizing a parameterized quantum circuit on a training data set, and subsequently making predictions on a testing data set (i.e., generalizing). In this work, we provide a comprehensive study of generalization performance in QML after training on a limited number $N$ of training data points. We show that the generalization error of a quantum machine learning model with $T$ trainable gates scales at worst as $\sqrt{T/N}$. When only $K \ll T$ gates have undergone substantial change in the optimization process, we prove that the generalization error improves to $\sqrt{K / N}$. Our results imply that the compiling of unitaries into a polynomial number of native gates, a crucial application for the quantum computing industry that typically uses exponential-size training data, can be sped up significantly. We also show that classification of quantum states across a phase transition with a quantum convolutional neural network requires only a very small training data set. Other potential applications include learning quantum error correcting codes or quantum dynamical simulation. Our work injects new hope into the field of QML, as good generalization is guaranteed from few training data. | N9: http://arxiv.org/abs/2111.05292v2
A10: 9 | B10: Multiclass classification using quantum convolutional neural networks with hybrid quantum-classical learning | C10: Denis Bokhan and Alena S Mastiukova and Aleksey S Boev and Dmitrii N Trubnikov and Aleksey K Fedorov | D10: Front. Phys. 10, 1069985 (2022) | E10: article | F10: 10.3389/fphy.2022.1069985 | G10: Exclude | H10: EC5 | K10: Multiclass classification is of great interest for various applications, for example, it is a common task in computer vision, where one needs to categorize an image into three or more classes. Here we propose a quantum machine learning approach based on quantum convolutional neural networks for solving the multiclass classification problem. The corresponding learning procedure is implemented via TensorFlowQuantum as a hybrid quantum-classical (variational) model, where quantum output results are fed to the softmax activation function with the subsequent minimization of the cross entropy loss via optimizing the parameters of the quantum circuit. Our conceptional improvements here include a new model for a quantum perceptron and an optimized structure of the quantum circuit. We use the proposed approach to solve a 4-class classification problem for the case of the MNIST dataset using eight qubits for data encoding and four ancilla qubits; previous results have been obtained for 3-class classification problems. Our results show that accuracies of our solution are similar to classical convolutional neural networks with comparable numbers of trainable parameters. We expect that our finding provide a new step towards the use of quantum neural networks for solving relevant problems in the NISQ era and beyond. | N10: http://arxiv.org/abs/2203.15368v2
A11: 10 | B11: Predict better with less training data using a QNN | C11: Barry D Reese and Marek Kowalik and Christian Metzl and Christian Bauckhage and Eldar Sultanow | E11: misc | G11: Exclude | H11: EC4 | K11: Over the past decade, machine learning revolutionized vision-based quality assessment for which convolutional neural networks (CNNs) have now become the standard. In this paper, we consider a potential next step in this development and describe a quanvolutional neural network (QNN) algorithm that efficiently maps classical image data to quantum states and allows for reliable image analysis. We practically demonstrate how to leverage quantum devices in computer vision and how to introduce quantum convolutions into classical CNNs. Dealing with a real world use case in industrial quality control, we implement our hybrid QNN model within the PennyLane framework and empirically observe it to achieve better predictions using much fewer training data than classical CNNs. In other words, we empirically observe a genuine quantum advantage for an industrial application where the advantage is due to superior data encoding. | N11: http://arxiv.org/abs/2206.03960v1
A12: 11 | B12: Case study on quantum convolutional neural network scalability | C12: Marina O Lisnichenko and Stanislav I Protasov | E12: misc | G12: Exclude | H12: EC5 | K12: One of the crucial tasks in computer science is the processing time reduction of various data types, i.e., images, which is important for different fields -- from medicine and logistics to virtual shopping. Compared to classical computers, quantum computers are capable of parallel data processing, which reduces the data processing time. This quality of quantum computers inspired intensive research of the potential of quantum technologies applicability to real-life tasks. Some progress has already revealed on a smaller volumes of the input data. In this research effort, I aimed to increase the amount of input data (I used images from 2 x 2 to 8 x 8), while reducing the processing time, by way of skipping intermediate measurement steps. The hypothesis was that, for increased input data, the omitting of intermediate measurement steps after each quantum convolution layer will improve output metric results and accelerate data processing. To test the hypothesis, I performed experiments to chose the best activation function and its derivative in each network. The hypothesis was partly confirmed in terms of output mean squared error (MSE) -- it dropped from 0.25 in the result of classical convolutional neural network (CNN) training to 0.23 in the result of quantum convolutional neural network (QCNN) training. In terms of the training time, however, which was 1.5 minutes for CNN and 4 hours 37 minutes in the least lengthy training iteration, the hypothesis was rejected. | N12: http://arxiv.org/abs/2207.07160v1
A13: 482 | B13: A Comparative Analysis of Hybrid Quantum Neural Networks in Binary Credit Defaulting Tasks | C13: Aditya Sengar and Aarya Vijayaraghavan and Jiwoo Hwang | D13: IEEE MIT Undergraduate Research Technology Conference, URTC 2023 - Proceedings | E13: inproceedings | F13: 10.1109/URTC60662.2023.10535032 | G13: Maybe | H13: QCNN used to create financial analytical models | I13: Exclude | J13: EC4 | K13: Quantum machine learning has been shown to offer exponential computational boosts compared to current classical models through the exploitation of quantum mechanical properties such as entanglement and superposition. The finance sub field of fin-Tech, where financial services are constructed around a customer's demands, is believed to benefit with the use of hybrid quantum-classical machine learning algorithms. Classical algorithms struggle to create accurate, complex, and prompt financial analytical models resulting in over 25% of small and medium sized financial institutions losing customers each year. This study explores whether a hybrid quantum neural network (QCNN) design provides a quantum advantage in either accuracy or time in the fin tech task of credit defaulting. The hybrid quantum neural network model uses a variational quantum circuit built on a continuous variable architecture. The data flow of the network consists of a classical network, quantum data encoding (which uses quantum squeezers, interferometers, displacement, and Kerr gates), QCNN, and measurement. Although the quantum model took a longer time to train, it reported a higher prediction accuracy of 97.63% compared to 91.20% for the classical network. This work demonstrates the future implications of quantum integration in the financial field and the quantum advantage it offers on classification tasks. © 2023 IEEE.
A14: 460 | B14: A Comparative Study of Classical and Quantum Machine Learning Techniques for Industrial Defect Classification | C14: Antimo Angelino and Daniele D'Amato and Gennaro Galante and Enrico Landolfi and Alfredo Massa and Alfredo Troiano | D14: Proceedings - 2025 IEEE International Conference on Quantum Artificial Intelligence, QAI 2025 | E14: inproceedings | F14: 10.1109/QAI63978.2025.00074 | G14: Include | H14: QCNN for Industrial Defect Classification | I14: Include | J14: Passed by Mahmoud | K14: This work presents a comparative evaluation of classical and quantum machine learning models applied to a real-world industrial classification task. The use case is provided by MBDA and involves classifying images of surface-mount technology solder joints into three defect severity classes. To investigate the viability and performance trade-offs of quantum models under realistic constraints, we followed two parallel processing strategies. The first employs conventional deep learning architectures, namely YOLOv8 and a custom Convolutional Neural Network (CNN), trained on augmented full-resolution images. The second strategy compresses image data via a domainspecific method, enabling compatibility with quantum hardware constraints. We trained and evaluated different quantum machine learning models, including a Quantum Support Vector Machine (QSVM), a Variational Quantum Classifier (VQC), and a Quantum Convolutional Neural Network (QCNN). Our results highlight the trade-offs between expressivity and feasibility across classical and quantum approaches and provide insights into the applicability of quantum models in industrial scenarios. © 2025 IEEE.
A15: 408 | B15: A complex-valued embedding and quantum convolutional neural network-based fake news detection method | C15: Jiacheng Tang and Lianhe Shao and Quanli Gao and Xihan Wang | D15: Proceedings of SPIE - The International Society for Optical Engineering | E15: inproceedings | F15: 10.1117/12.3075824 | G15: Include | H15: QCNN used for Fake News Detection | I15: Exclude | J15: EC8 | K15: Recently, fake news has been on the rise, seriously affecting public perception and personal decision-making. Given that online fake news often contains multimedia elements, such information is more misleading than fake news in purely textual form and can spread more widely, it is significant to study multimodal fake news detection. However, the existing detection methods have a few problems: 1) The current tactics with better detection effect usually use Transformer to extract text features, which leads to insufficient extraction of news text features. 2) The existing methods usually use a cascade method to splice modal features and then directly feed them into the classifier, which leads to unsatisfactory detection results. Aiming at the above problems, we propose a quantum-inspired fake news detection method (CQFND). Specifically, the word embedding representation of the input text is converted to a complex form by using a complex-valued embedding layer (ComplexEmbedding) and weighted summation, and the text's feature representation is derived by weighted aggregation. The news image features are obtained by ViT, the two are vector spliced, and the results are processed by the introduced QCNN to finally obtain the detection results. The CQFND model is tested against other classical models on public datasets, and the results confirm that our approach outperforms others on some common indicators. © 2025 SPIE.
A16: 87 | B16: A Deep Quantum Convolutional Neural Network Based Facial Expression Recognition For Mental Health Analysis | C16: S Hossain and S Umer and R K Rout and H A Marzouqi | D16: IEEE Transactions on Neural Systems and Rehabilitation Engineering | E16: article | F16: 10.1109/TNSRE.2024.3385336 | G16: Include | H16: QCNN on Facial Expression Recognition | I16: Include | J16: Passed by Mahmoud | K16: The purpose of this work is to analyze how new technologies can enhance clinical practice while also examining the physical traits of emotional expressiveness of face expression in a number of psychiatric illnesses. Hence, in this work, an automatic facial expression recognition system has been proposed that analyzes static, sequential, or video facial images from medical healthcare data to detect emotions in people's facial regions. The proposed method has been implemented in five steps. The first step is image preprocessing, where a facial region of interest has been segmented from the input image. The second component includes a classical deep feature representation and the quantum part that involves successive sets of quantum convolutional layers followed by random quantum variational circuits for feature learning. Here, the proposed system has attained a faster training approach using the proposed quantum convolutional neural network approach that takes $\mathbb \{O\}\{(\}\text \{log\}\{(\}\{n\}\{)\}\{)\}$ time. In contrast, the classical convolutional neural network models have $\mathbb \{O\}\{(\}\{n\}^\{\{2\}\}\{)\}$ time. Additionally, some performance improvement techniques, such as image augmentation, fine-tuning, matrix normalization, and transfer learning methods, have been applied to the recognition system. Finally, the scores due to classical and quantum deep learning models are fused to improve the performance of the proposed method. Extensive experimentation with Karolinska-directed emotional faces (KDEF), Static Facial Expressions in the Wild (SFEW 2.0), and Facial Expression Recognition 2013 (FER-2013) benchmark databases and compared with other state-of-the-art methods that show the improvement of the proposed system.
A17: 31 | B17: A Distributed Hybrid Quantum Convolutional Neural Network for Medical Image Classification | C17: Yangyang Li and Zhengya Qia and Yuelin Lia and Haorui Yanga and Ronghua Shanga and Licheng Jiaoa | E17: misc | G17: Include | H17: Medical QCNN | I17: Include | J17: Passed by Mahmoud | K17: Medical images are characterized by intricate and complex features, requiring interpretation by physicians with medical knowledge and experience. Classical neural networks can reduce the workload of physicians, but can only handle these complex features to a limited extent. Theoretically, quantum computing can explore a broader parameter space with fewer parameters, but it is currently limited by the constraints of quantum hardware.Considering these factors, we propose a distributed hybrid quantum convolutional neural network based on quantum circuit splitting. This model leverages the advantages of quantum computing to effectively capture the complex features of medical images, enabling efficient classification even in resource-constrained environments. Our model employs a quantum convolutional neural network (QCNN) to extract high-dimensional features from medical images, thereby enhancing the model's expressive capability.By integrating distributed techniques based on quantum circuit splitting, the 8-qubit QCNN can be reconstructed using only 5 qubits.Experimental results demonstrate that our model achieves strong performance across 3 datasets for both binary and multiclass classification tasks. Furthermore, compared to recent technologies, our model achieves superior performance with fewer parameters, and experimental results validate the effectiveness of our model. | N17: http://arxiv.org/abs/2501.06225v1
A18: 17 | B18: Quaternion Convolutional Neural Networks: Current Advances and Future Directions | C18: Gerardo Altamirano-Gomez and Carlos Gershenson | D18: Advances in Applied Clifford Algebras, 34(4):42, 2024 | E18: article | F18: 10.1007/s00006-024-01350-x | G18: Exclude | H18: EC4 | K18: Since their first applications, Convolutional Neural Networks (CNNs) have solved problems that have advanced the state-of-the-art in several domains. CNNs represent information using real numbers. Despite encouraging results, theoretical analysis shows that representations such as hyper-complex numbers can achieve richer representational capacities than real numbers, and that Hamilton products can capture intrinsic interchannel relationships. Moreover, in the last few years, experimental research has shown that Quaternion-Valued CNNs (QCNNs) can achieve similar performance with fewer parameters than their real-valued counterparts. This paper condenses research in the development of QCNNs from its very beginnings. We propose a conceptual organization of current trends and analyze the main building blocks used in the design of QCNN models. Based on this conceptual organization, we propose future directions of research. | N18: http://arxiv.org/abs/2307.08663v1
A19: 18 | B19: A Post-Training Approach for Mitigating Overfitting in Quantum Convolutional Neural Networks | C19: Aakash Ravindra Shinde and Charu Jain and Amir Kalev | D19: Phys Rev A 110 042409 (2024) | E19: article | F19: 10.1103/PhysRevA.110.042409 | G19: Exclude | H19: EC5 | K19: Quantum convolutional neural network (QCNN), an early application for quantum computers in the NISQ era, has been consistently proven successful as a machine learning (ML) algorithm for several tasks with significant accuracy. Derived from its classical counterpart, QCNN is prone to overfitting. Overfitting is a typical shortcoming of ML models that are trained too closely to the availed training dataset and perform relatively poorly on unseen datasets for a similar problem. In this work we study post-training approaches for mitigating overfitting in QCNNs. We find that a straightforward adaptation of a classical post-training method, known as neuron dropout, to the quantum setting leads to a significant and undesirable consequence: a substantial decrease in success probability of the QCNN. We argue that this effect exposes the crucial role of entanglement in QCNNs and the vulnerability of QCNNs to entanglement loss. Hence, we propose a parameter adaptation method as an alternative method. Our method is computationally efficient and is found to successfully handle overfitting in the test cases. | N19: http://arxiv.org/abs/2309.01829v2
A20: 19 | B20: Quantum Inception Score | C20: Akira Sone and Akira Tanji and Naoki Yamamoto | D20: Phys. Rev. Research 6, 033198 (2024) | E20: article | F20: 10.1103/PhysRevResearch.6.033198 | G20: Exclude | H20: EC4 | K20: Motivated by the great success of classical generative models in machine learning, enthusiastic exploration of their quantum version has recently started. To depart on this journey, it is important to develop a relevant metric to evaluate the quality of quantum generative models; in the classical case, one such example is the (classical) inception score (cIS). In this paper, as a natural extension of cIS, we propose the quantum inception score (qIS) for quantum generators. Importantly, qIS relates the quality to the Holevo information of the quantum channel that classifies a given dataset. In this context, we show several properties of qIS. First, qIS is greater than or equal to the corresponding cIS, which is defined through projection measurements on the system output. Second, the difference between qIS and cIS arises from the presence of quantum coherence, as characterized by the resource theory of asymmetry. Third, when a set of entangled generators is prepared, there exists a classifying process leading to the further enhancement of qIS. Fourth, we harness the quantum fluctuation theorem to characterize the physical limitation of qIS. Finally, we apply qIS to assess the quality of the one-dimensional spin chain model as a quantum generative model, with the quantum convolutional neural network as a quantum classifier, for the phase classification problem in the quantum many-body physics. | N20: http://arxiv.org/abs/2311.12163v4
A21: 20 | B21: Impact of Data Augmentation on QCNNs | C21: Leting Zhouli and Peiyong Wang and Udaya Parampalli | E21: misc | G21: Exclude | H21: EC7 | K21: In recent years, Classical Convolutional Neural Networks (CNNs) have been applied for image recognition successfully. Quantum Convolutional Neural Networks (QCNNs) are proposed as a novel generalization to CNNs by using quantum mechanisms. The quantum mechanisms lead to an efficient training process in QCNNs by reducing the size of input from $N$ to $log_2N$. This paper implements and compares both CNNs and QCNNs by testing losses and prediction accuracy on three commonly used datasets. The datasets include the MNIST hand-written digits, Fashion MNIST and cat/dog face images. Additionally, data augmentation (DA), a technique commonly used in CNNs to improve the performance of classification by generating similar images based on original inputs, is also implemented in QCNNs. Surprisingly, the results showed that data augmentation didn't improve QCNNs performance. The reasons and logic behind this result are discussed, hoping to expand our understanding of Quantum machine learning theory. | N21: http://arxiv.org/abs/2312.00358v1
A22: 118 | B22: A Hybrid Quantum-Classical Approach for Multi-Class Skin Disease Classification Using a 4-Qubit Model | C22: Aravinda and Emerson Raja Joseph and Sultan Alasmari | D22: IEEE Access | E22: article | F22: 10.1109/ACCESS.2025.3581030 | G22: Include | H22: QCNN against Q-C Skin Disease Classification | K22: Quantum machine learning (QML) presents a promising avenue for addressing complex classification challenges, yet its application in medical imaging remains largely unexplored. This work introduces a hybrid quantum-classical framework designed to classify skin diseases, Chickenpox, Measles, Monkeypox, and Normal, using a 4 qubit quantum system. The framework integrates a Quantum Convolutional Neural Network (QCNN) for feature extraction and a Variational Quantum Classifier (VQC) for classification, processing a dataset of 770 images with significant class imbalance. We employ a class-weighted loss function with weights wyi = [3.0, 3.5, 0.6, 0.4] to address this imbalance, ensuring balanced representation across all classes. The model is optimized using Simultaneous Perturbation Stochastic Approximation (SPSA) over 150 iterations, achieving a test accuracy 70.13% on a subset of 154 images, representing 20% of the dataset. This marks a substantial improvement over both a random baseline of 25% and a prior run that achieved 37.66% accuracy, which was skewed toward the majority class. Principal Component Analysis (PCA) reduces image features to a 4-dimensional representation, enabling compatibility with the quantum system. The QCNN extracts these features, while the VQC performs classification based on measurements from 1024 shots on the QASM simulator. To ensure practical reusability, the trained model, including quantum circuits, optimized parameters, and PCA transformations, is saved for future deployment. Validation on a separate set of 24 samples (6 per class) yields 70.83% accuracy (17 out of 24 correct predictions), demonstrating the model’s generalization capabilities. While the performance falls short of classical benchmarks, this study establishes the feasibility of QML with minimal qubits, paving the way for quantum driven diagnostics in resource constrained environments. © 2013 IEEE.
A23: 22 | B23: ResQuNNs: Towards Enabling Deep Learning in Quantum Convolution Neural Networks | C23: Muhammad Kashif and Muhammad Shafique | D23: Scientific Reports 15, no. 1 (2025) | E23: article | F23: 10.1038/s41598-025-06035-4 | G23: Exclude | H23: EC4 | K23: In this paper, we present a novel framework for enhancing the performance of Quanvolutional Neural Networks (QuNNs) by introducing trainable quanvolutional layers and addressing the critical challenges associated with them. Traditional quanvolutional layers, although beneficial for feature extraction, have largely been static, offering limited adaptability. Unlike state-of-the-art, our research overcomes this limitation by enabling training within these layers, significantly increasing the flexibility and potential of QuNNs. However, the introduction of multiple trainable quanvolutional layers induces complexities in gradient-based optimization, primarily due to the difficulty in accessing gradients across these layers. To resolve this, we propose a novel architecture, Residual Quanvolutional Neural Networks (ResQuNNs), leveraging the concept of residual learning, which facilitates the flow of gradients by adding skip connections between layers. By inserting residual blocks between quanvolutional layers, we ensure enhanced gradient access throughout the network, leading to improved training performance. Moreover, we provide empirical evidence on the strategic placement of these residual blocks within QuNNs. Through extensive experimentation, we identify an efficient configuration of residual blocks, which enables gradients across all the layers in the network that eventually results in efficient training. Our findings suggest that the precise location of residual blocks plays a crucial role in maximizing the performance gains in QuNNs. Our results mark a substantial step forward in the evolution of quantum deep learning, offering new avenues for both theoretical development and practical quantum computing applications. | N23: http://arxiv.org/abs/2402.09146v6
A24: 23 | B24: Multi-GPU-Enabled Hybrid Quantum-Classical Workflow in Quantum-HPC Middleware: Applications in Quantum Simulations | C24: Kuan-Cheng Chen and Xiaoren Li and Xiaotian Xu and Yun-Yuan Wang and Chen-Yu Liu | E24: misc | G24: Exclude | H24: EC4 | K24: Achieving high-performance computation on quantum systems presents a formidable challenge that necessitates bridging the capabilities between quantum hardware and classical computing resources. This study introduces an innovative distribution-aware Quantum-Classical-Quantum (QCQ) architecture, which integrates cutting-edge quantum software framework works with high-performance classical computing resources to address challenges in quantum simulation for materials and condensed matter physics. At the heart of this architecture is the seamless integration of VQE algorithms running on QPUs for efficient quantum state preparation, Tensor Network states, and QCNNs for classifying quantum states on classical hardware. For benchmarking quantum simulators, the QCQ architecture utilizes the cuQuantum SDK to leverage multi-GPU acceleration, integrated with PennyLane's Lightning plugin, demonstrating up to tenfold increases in computational speed for complex phase transition classification tasks compared to traditional CPU-based methods. This significant acceleration enables models such as the transverse field Ising and XXZ systems to accurately predict phase transitions with a 99.5% accuracy. The architecture's ability to distribute computation between QPUs and classical resources addresses critical bottlenecks in Quantum-HPC, paving the way for scalable quantum simulation. The QCQ framework embodies a synergistic combination of quantum algorithms, machine learning, and Quantum-HPC capabilities, enhancing its potential to provide transformative insights into the behavior of quantum systems across different scales. As quantum hardware continues to improve, this hybrid distribution-aware framework will play a crucial role in realizing the full potential of quantum computing by seamlessly integrating distributed quantum resources with the state-of-the-art classical computing infrastructure. | N24: http://arxiv.org/abs/2403.05828v2
A25: 24 | B25: Optimizing Quantum Convolutional Neural Network Architectures for Arbitrary Data Dimension | C25: Changwon Lee and Israel F Araujo and Dongha Kim and Junghan Lee and Siheon Park and Ju-Young Ryu and Daniel K Park | D25: Frontiers in Physics 13 1529188 (2025) | E25: article | F25: 10.3389/fphy.2025.1529188 | G25: Exclude | H25: EC7 | K25: Quantum convolutional neural networks (QCNNs) represent a promising approach in quantum machine learning, paving new directions for both quantum and classical data analysis. This approach is particularly attractive due to the absence of the barren plateau problem, a fundamental challenge in training quantum neural networks (QNNs), and its feasibility. However, a limitation arises when applying QCNNs to classical data. The network architecture is most natural when the number of input qubits is a power of two, as this number is reduced by a factor of two in each pooling layer. The number of input qubits determines the dimensions (i.e. the number of features) of the input data that can be processed, restricting the applicability of QCNN algorithms to real-world data. To address this issue, we propose a QCNN architecture capable of handling arbitrary input data dimensions while optimizing the allocation of quantum resources such as ancillary qubits and quantum gates. This optimization is not only important for minimizing computational resources, but also essential in noisy intermediate-scale quantum (NISQ) computing, as the size of the quantum circuits that can be executed reliably is limited. Through numerical simulations, we benchmarked the classification performance of various QCNN architectures when handling arbitrary input data dimensions on the MNIST and Breast Cancer datasets. The results validate that the proposed QCNN architecture achieves excellent classification performance while utilizing a minimal resource overhead, providing an optimal solution when reliable quantum computation is constrained by noise and imperfections. | N25: http://arxiv.org/abs/2403.19099v1
A26: 382 | B26: A HYBRID QUANTUM-INSPIRED CNN ARCHITECTURE FOR EFFICIENT AND ACCURATE BRAIN TUMOR CLASSIFICATION WITH EXPLAINABILITY ANALYSIS | C26: Sheethal and Amudha | D26: Journal of Theoretical and Applied Information Technology | E26: article | G26: Include | H26: QCNN for Brain Tumor Classification | I26: Exclude | J26: EC4 | K26: Brain tumors are considered one of the serious types of cancer and catching them early is crucial for better patient results. The use of Magnetic Resonance Imaging (MRI) plays a role in spotting and categorizing brain tumors; however, it can be tough and time consuming for radiologists to interpret these images. To address this issue, this study introduces a Quantum Inspired Convolutional Neural Network (QCNN) that integrates concepts from quantum mechanics, such as superposition and entanglement, with traditional Convolutional Neural Network (CNN) architectures. This innovative approach enhances feature extraction capabilities, allowing the model to recognize intricate patterns within MRI images more effectively. The QCNN achieved impressive results, reaching a peak validation accuracy of 99.44% and demonstrating significantly improved classification for various types of brain tumors, including Glioma and Meningitis. These findings highlight the potential of the QCNN framework to revolutionize tumor detection, offering radiologists a powerful tool that enhances diagnostic accuracy and efficiency in clinical practice, ultimately leading to better patient care and outcomes in the medical imaging field. © Little Lion Scientific.
A27: 26 | B27: Quantum Adjoint Convolutional Layers for Effective Data Representation | C27: Ren-Xin Zhao and Shi Wang and Yaonan Wang | E27: misc | F27: 10.1109/TCYB.2025.3567090 | G27: Exclude | H27: EC7 | K27: Quantum Convolutional Layer (QCL) is considered as one of the core of Quantum Convolutional Neural Networks (QCNNs) due to its efficient data feature extraction capability. However, the current principle of QCL is not as mathematically understandable as Classical Convolutional Layer (CCL) due to its black-box structure. Moreover, classical data mapping in many QCLs is inefficient. To this end, firstly, the Quantum Adjoint Convolution Operation (QACO) consisting of a quantum amplitude encoding and its inverse is theoretically shown to be equivalent to the quantum normalization of the convolution operation based on the Frobenius inner product while achieving an efficient characterization of the data. Subsequently, QACO is extended into a Quantum Adjoint Convolutional Layer (QACL) by Quantum Phase Estimation (QPE) to compute all Frobenius inner products in parallel. At last, comparative simulation experiments are carried out on PennyLane and TensorFlow platforms, mainly for the two cases of kernel fixed and unfixed in QACL. The results demonstrate that QACL with the insight of special quantum properties for the same images, provides higher training accuracy in MNIST and Fashion MNIST classification experiments, but sacrifices the learning performance to some extent. Predictably, our research lays the foundation for the development of efficient and interpretable quantum convolutional networks and also advances the field of quantum machine vision. | N27: http://arxiv.org/abs/2404.17378v1
A28: 27 | B28: Permutation-equivariant quantum convolutional neural networks | C28: Sreetama Das and Filippo Caruso | D28: Quantum Sci. Technol. 10 015030 (2025) | E28: article | F28: 10.1088/2058-9565/ad8e80 | G28: Exclude | H28: EC7 | K28: The Symmetric group $S_{n}$ manifests itself in large classes of quantum systems as the invariance of certain characteristics of a quantum state with respect to permuting the qubits. The subgroups of $S_{n}$ arise, among many other contexts, to describe label symmetry of classical images with respect to spatial transformations, e.g. reflection or rotation. Equipped with the formalism of geometric quantum machine learning, in this work we propose the architectures of equivariant quantum convolutional neural networks (EQCNNs) adherent to $S_{n}$ and its subgroups. We demonstrate that a careful choice of pixel-to-qubit embedding order can facilitate easy construction of EQCNNs for small subgroups of $S_{n}$. Our novel EQCNN architecture corresponding to the full permutation group $S_{n}$ is built by applying all possible QCNNs with equal probability, which can also be conceptualized as a dropout strategy in quantum neural networks. For subgroups of $S_{n}$, our numerical results using MNIST datasets show better classification accuracy than non-equivariant QCNNs. The $S_{n}$-equivariant QCNN architecture shows significantly improved training and test performance than non-equivariant QCNN for classification of connected and non-connected graphs. When trained with sufficiently large number of data, the $S_{n}$-equivariant QCNN shows better average performance compared to $S_{n}$-equivariant QNN . These results contribute towards building powerful quantum machine learning architectures in permutation-symmetric systems. | N28: http://arxiv.org/abs/2404.18198v1
A29: 28 | B29: Quanv4EO: Empowering Earth Observation by means of Quanvolutional Neural Networks | C29: Alessandro Sebastianelli and Francesco Mauro and Giulia Ciabatti and Dario Spiller and Bertrand Le Saux and Paolo Gamba and Silvia Ullo | E29: misc | G29: Exclude | H29: EC4 | K29: A significant amount of remotely sensed data is generated daily by many Earth observation (EO) spaceborne and airborne sensors over different countries of our planet. Different applications use those data, such as natural hazard monitoring, global climate change, urban planning, and more. Many challenges are brought by the use of these big data in the context of remote sensing applications. In recent years, employment of machine learning (ML) and deep learning (DL)-based algorithms have allowed a more efficient use of these data but the issues in managing, processing, and efficiently exploiting them have even increased since classical computers have reached their limits. This article highlights a significant shift towards leveraging quantum computing techniques in processing large volumes of remote sensing data. The proposed Quanv4EO model introduces a quanvolution method for preprocessing multi-dimensional EO data. First its effectiveness is demonstrated through image classification tasks on MNIST and Fashion MNIST datasets, and later on, its capabilities on remote sensing image classification and filtering are shown. Key findings suggest that the proposed model not only maintains high precision in image classification but also shows improvements of around 5\% in EO use cases compared to classical approaches. Moreover, the proposed framework stands out for its reduced parameter size and the absence of training quantum kernels, enabling better scalability for processing massive datasets. These advancements underscore the promising potential of quantum computing in addressing the limitations of classical algorithms in remote sensing applications, offering a more efficient and effective alternative for image data classification and analysis. | N29: http://arxiv.org/abs/2407.17108v1
A30: 29 | B30: Statistical Analysis of the Impact of Quaternion Components in Convolutional Neural Networks | C30: Gerardo Altamirano-Gómez and Carlos Gershenson | E30: misc | G30: Exclude | H30: EC4 | K30: In recent years, several models using Quaternion-Valued Convolutional Neural Networks (QCNNs) for different problems have been proposed. Although the definition of the quaternion convolution layer is the same, there are different adaptations of other atomic components to the quaternion domain, e.g., pooling layers, activation functions, fully connected layers, etc. However, the effect of selecting a specific type of these components and the way in which their interactions affect the performance of the model still unclear. Understanding the impact of these choices on model performance is vital for effectively utilizing QCNNs. This paper presents a statistical analysis carried out on experimental data to compare the performance of existing components for the image classification problem. In addition, we introduce a novel Fully Quaternion ReLU activation function, which exploits the unique properties of quaternion algebra to improve model performance. | N30: http://arxiv.org/abs/2409.00140v1
A31: 330 | B31: A new quantum AI -performance analysis of low-power VLSI circuits in IoT devices using quantum machine learning techniques | C31: Manan Mujahid Md and Deepa Jose | D31: Quantum Information Processing | E31: article | F31: 10.1007/s11128-026-05149-6 | G31: Maybe | H31: Check QCNN results | I31: Exclude | J31: EC8 | K31: Recent advancements in the Internet of Things (IoT) have heightened the demand for energy efficient, high-performance Very Large-Scale Integration (VLSI) circuits. While machine learning has been widely employed for performance analysis and optimization, the integration of quantum computing concepts is reshaping this domain. This paper presents a comprehensive framework that leverages both classical deep learning and quantum-enhanced algorithms to analyze and optimize low-power VLSI circuits in IoT devices. Advanced Quantum AI techniques—specifically, the Proposed Quantum Support Vector Machine (QSVM)—are applied alongside conventional models (QANN, QCNN, QLSTM, and QAdaptive CNN-LSTM) to enable high-dimensional feature transformations and exponential parallelism in analysis. Experimental results demonstrate that the QAdaptive CNN-LSTM achieves 94.5% accuracy, 92.0% precision, 93.0% recall, 92.5% F1-score, and an MSE of 0.05, significantly outperforming QANN (82.5% accuracy, 81.2% precision, 81.0% recall, 81.1% F1, MSE 0.15), QCNN (86.5% accuracy, 84.0% precision, 81.5% recall, 82.7% F1, MSE 0.11), and QLSTM (84.0% accuracy, 83.5% precision, 85.5% recall, 84.5% F1, MSE 0.20). Moreover, the Proposed QSVM model attains the highest accuracy of 96.0%, with 94.5% precision, 95.0% recall, 94.7% F1-score, and the lowest MSE of 0.035, underscoring the strong potential of quantum-enhanced learning in VLSI analysis. These quantifiable improvements translate into superior prediction accuracy, faster convergence, and better energy-timing optimization under resource-constrained IoT scenarios. The hybrid quantum–classical analytical approach not only enhances predictive maintenance and optimization of VLSI circuits but also accelerates the development of sustainable, scalable, and energy-efficient IoT ecosystems. © The Author(s), under exclusive licence to Springer Science+Business Media, LLC, part of Springer Nature 2026.
A32: 268 | B32: A New Quantum Circuits of Quantum Convolutional Neural Network for X-Ray Images Classification | C32: Mohammed Yousif and Belal Al-Khateeb and Begonya Garcia-Zapirain | D32: IEEE Access | E32: article | F32: 10.1109/ACCESS.2024.3396411 | G32: Include | H32: QCNN for X-Ray Classification | K32: A common model for classifying images is the convolutional neural network (CNN), which has the benefit of effectively using data correlation information. Despite their remarkable success, classical CNNs may face challenges in achieving further improvements in accuracy, computational efficiency, explainability, and generalization. However, if the specified data dimension or model grows too large, CNN becomes difficult to train effectively with a slowdown processing. In order to address a problem using CNN utilizing quantum computing, Quantum Convolutional Neural Network (QCNN) proposes a novel quantum solution or enhances the functionality of an existing learning model in terms of processing time during training. This paper presents a comparative analysis between classical Convolutional Neural Networks (CNNs) and a novel quantum circuit architecture tailored for image-based tasks, emphasizing the adaptability and versatility of quantum circuits in enhancing feature extraction capabilities and then final accuracy and processing time. A MNIST and covidx-cxr3 datasets was used to train quantum-CNN models, and the results of these comparisons were made with traditional CNN performance. The results demonstrate that the suggested QCNN beat the traditional CNN in terms of recognition accuracy and processing speed (process time) when combined with cutting-edge feature extraction techniques. This superiority is particularly evident when trained on the covidx-cxr3 dataset, highlighting the potential for quantum computing to revolutionize image classification tasks. © 2013 IEEE.
A33: 32 | B33: QuFeX: Quantum feature extraction module for hybrid quantum-classical deep neural networks | C33: Naman Jain and Amir Kalev | D33: Quantum Sci. Technol. 11 015017 (2026) | E33: article | F33: 10.1088/2058-9565/ae24a8 | G33: Exclude | H33: EC4 | K33: We introduce Quantum Feature Extraction (QuFeX), a novel quantum machine learning module. The proposed module enables feature extraction in a reduced-dimensional space, significantly decreasing the number of parallel evaluations required in typical quantum convolutional neural network architectures. Its design allows seamless integration into deep classical neural networks, making it particularly suitable for hybrid quantum-classical models. As an application of QuFeX, we propose Qu-Net -- a hybrid architecture which integrates QuFeX at the bottleneck of a U-Net architecture. The latter is widely used for image segmentation tasks such as medical imaging and autonomous driving. Our numerical analysis indicates that the Qu-Net can achieve superior segmentation performance compared to a U-Net baseline. These results highlight the potential of QuFeX to enhance deep neural networks by leveraging hybrid computational paradigms, providing a path towards a robust framework for real-world applications requiring precise feature extraction. | N33: http://arxiv.org/abs/2501.13165v2
A34: 475 | B34: A Novel Approach to Derma Quantum (Skin Disease Detection and Classification Using ResNet50 and QCNN) | C34: Harsh Kumar and Pranesh Sharma and Ajina and Nithin M Kannal and Ujjwal Kumar | D34: 2024 2nd International Conference on Computing and Data Analytics, ICCDA 2024 - Proceedings | E34: inproceedings | F34: 10.1109/ICCDA64887.2024.10867304 | G34: Include | H34: QCNN with ResNet for Skin Diseases | K34: Multiclass disease classification is a crucial task in medical diagnostics, but achieving high accuracy across diverse disease categories remains challenging. This paper presents a novel approach that integrates Quantum Convolutional Neural Networks (QCNN) with the ResNet architecture to enhance multiclass skin disease classification. The model utilizes quantum computing principles to improve feature extraction and classification performance. We evaluate the model on a dataset comprising 16 skin disease classes from the DermNet dataset, covering both common and rare conditions like acne, melanoma, Eczema, Seborrheic Keratoses, Tinea Ringworm, Bullous disease, Poison Ivy, Psoriasis, Vascular Tumors, etc. Experimental results demonstrate that our QCNN-ResNet model achieves a classification accuracy of 86%, significantly surpassing the 66% accuracy of traditional ResNet models. This improvement is attributed to the enhanced feature representation provided by quantum layers, which capture complex patterns in medical images more effectively. Furthermore, the model exhibits robustness to noisy data, maintaining high accuracy across varying image quality levels. These findings highlight the potential of quantumenhanced neural networks in advancing medical diagnostics. Future research will explore scaling the model to larger datasets and extending its application to other medical imaging domains. © 2024 IEEE.
A35: 449 | B35: A Novel Framework For Brain Disease Classification Using Quantum Convolutional Neural Network | C35: Sanskriti Chandra and Shivam Saxena and Santosh Kumar and Mithilesh Kumar Chaube and Narendra Kuber Bodhey | D35: Proceedings of 2022 IEEE International Women in Engineering (WIE) Conference on Electrical and Computer Engineering, WIECON-ECE 2022 | E35: inproceedings | F35: 10.1109/WIECON-ECE57977.2022.10150851 | G35: Include | H35: QCNN for Brain Disease Classification | K35: More than 3,410 children and teens (under the age of 20) in India suffer from catastrophic brain disorders and the creation of abnormal brain cells each year, according to recent reports on the country's rapid increase in brain ailments. It is difficult to quantify the survival rate of human patients due to the rarity, variability, and abnormal development of tumors. These patients cannot be accurately predicted using machine learning approaches for early diagnosis. These methods need a huge amount of discriminatory information and processing time based on annotated limited brain image datasets to classify diseases. To solve this problem, we proposed a novel model based on Quantum Convolutional Neural Network techniques for early diagnosis of tumors in a less invasive manner that may reduce the number of operations and more precisely define the kind of therapy needed. The proposed framework uses image processing techniques to remove noise and other specific artifacts from the brain images. After that, the processed images are segmented into distinct regions of interest using machine learning techniques. The suggested framework uses deep quantum approaches to identify brain disorders based on extracted discriminating characteristics from the brain images, such as textures and qubit features, enabling reliable prediction of brain disorders. The proposed system provided 93.99% accuracy for the accurate prediction of brain diseases using classical models and 88.7% accuracy using the Quantum Convolutional Neural Network (QCNN) model. © 2022 IEEE.
A36: 35 | B36: TunnElQNN: A Hybrid Quantum-classical Neural Network for Efficient Learning | C36: A H Abbas | E36: misc | G36: Exclude | H36: EC4 | K36: Hybrid quantum-classical neural networks (HQCNNs) represent a promising frontier in machine learning, leveraging the complementary strengths of both models. In this work, we propose the development of TunnElQNN, a non-sequential architecture composed of alternating classical and quantum layers. Within the classical component, we employ the Tunnelling Diode Activation Function (TDAF), inspired by the I-V characteristics of quantum tunnelling. We evaluate the performance of this hybrid model on a synthetic dataset of interleaving half-circle for multi-class classification tasks with varying degrees of class overlap. The model is compared against a baseline hybrid architecture that uses the conventional ReLU activation function (ReLUQNN). Our results show that the TunnElQNN model consistently outperforms the ReLUQNN counterpart. Furthermore, we analyse the decision boundaries generated by TunnElQNN under different levels of class overlap and compare them to those produced by a neural network implementing TDAF within a fully classical architecture. These findings highlight the potential of integrating physics-inspired activation functions with quantum components to enhance the expressiveness and robustness of hybrid quantum-classical machine learning architectures. | N36: http://arxiv.org/abs/2505.00933v2
A37: 36 | B37: Efficient Quantum Convolutional Neural Networks for Image Classification: Overcoming Hardware Constraints | C37: Peter Röseler and Oliver Schaudt and Helmut Berg and Christian Bauckhage and Matthias Koch | E37: misc | G37: Exclude | H37: EC7 | K37: While classical convolutional neural networks (CNNs) have revolutionized image classification, the emergence of quantum computing presents new opportunities for enhancing neural network architectures. Quantum CNNs (QCNNs) leverage quantum mechanical properties and hold potential to outperform classical approaches. However, their implementation on current noisy intermediate-scale quantum (NISQ) devices remains challenging due to hardware limitations. In our research, we address this challenge by introducing an encoding scheme that significantly reduces the input dimensionality. We demonstrate that a primitive QCNN architecture with 49 qubits is sufficient to directly process $28\times 28$ pixel MNIST images, eliminating the need for classical dimensionality reduction pre-processing. Additionally, we propose an automated framework based on expressibility, entanglement, and complexity characteristics to identify the building blocks of QCNNs, parameterized quantum circuits (PQCs). Our approach demonstrates advantages in accuracy and convergence speed with a similar parameter count compared to both hybrid QCNNs and classical CNNs. We validated our experiments on IBM's Heron r2 quantum processor, achieving $96.08\%$ classification accuracy, surpassing the $71.74\%$ benchmark of traditional approaches under identical training conditions. These results represent one of the first implementations of image classifications on real quantum hardware and validate the potential of quantum computing in this area. | N37: http://arxiv.org/abs/2505.05957v2
A38: 37 | B38: QGAN-based data augmentation for hybrid quantum-classical neural networks | C38: Run-Ze He and Jun-Jian Su and Su-Juan Qin and Zheng-Ping Jin and Fei Gao | E38: misc | G38: Exclude | H38: EC4 | K38: Quantum neural networks converge faster and achieve higher accuracy than classical models. However, data augmentation in quantum machine learning remains underexplored. To tackle data scarcity, we integrate quantum generative adversarial networks (QGANs) with hybrid quantum-classical neural networks (HQCNNs) to develop an augmentation framework. We propose two strategies: a general approach to enhance data processing and classification across HQCNNs, and a customized strategy that dynamically generates samples tailored to the HQCNN's performance on specific data categories, improving its ability to learn from complex datasets. Simulation experiments on the MNIST dataset demonstrate that QGAN outperforms traditional data augmentation methods and classical GANs. Compared to baseline DCGAN, QGAN achieves comparable performance with half the parameters, balancing efficiency and effectiveness. This suggests that QGANs can simplify models and generate high-quality data, enhancing HQCNN accuracy and performance. These findings pave the way for applying quantum data augmentation techniques in machine learning. | N38: http://arxiv.org/abs/2505.24780v1
A39: 38 | B39: Boosting Classification with Quantum-Inspired Augmentations | C39: Matthias Tschöpe and Vitor Fortes Rey and Sogo Pierre Sanon and Paul Lukowicz and Nikolaos Palaiodimopoulos and Maximilian Kiefer-Emmanouilidis | E39: misc | G39: Exclude | H39: EC4 | K39: Understanding the impact of small quantum gate perturbations, which are common in quantum digital devices but absent in classical computers, is crucial for identifying potential advantages in quantum machine learning. While these perturbations are typically seen as detrimental to quantum computation, they can actually enhance performance by serving as a natural source of data augmentation. Additionally, they can often be efficiently simulated on classical hardware, enabling quantum-inspired approaches to improve classical machine learning methods. In this paper, we investigate random Bloch sphere rotations, which are fundamental SU(2) transformations, as a simple yet effective quantum-inspired data augmentation technique. Unlike conventional augmentations such as flipping, rotating, or cropping, quantum transformations lack intuitive spatial interpretations, making their application to tasks like image classification less straightforward. While common quantum augmentation methods rely on applying quantum models or trainable quanvolutional layers to classical datasets, we focus on the direct application of small-angle Bloch rotations and their effect on classical data. Using the large-scale ImageNet dataset, we demonstrate that our quantum-inspired augmentation method improves image classification performance, increasing Top-1 accuracy by 3%, Top-5 accuracy by 2.5%, and the F$_1$ score from 8% to 12% compared to standard classical augmentation methods. Finally, we examine the use of stronger unitary augmentations. Although these transformations preserve information in principle, they result in visually unrecognizable images with potential applications for privacy computations. However, we show that our augmentation approach and simple SU(2) transformations do not enhance differential privacy and discuss the implications of this limitation. | N39: http://arxiv.org/abs/2506.22241v1
A40: 39 | B40: Selective Feature Re-Encoded Quantum Convolutional Neural Network with Joint Optimization for Image Classification | C40: Shaswata Mahernob Sarkar and Sheikh Iftekhar Ahmed and Jishnu Mahmud and Shaikh Anowarul Fattah and Gaurav Sharma | E40: misc | G40: Exclude | H40: EC7 | K40: Quantum Machine Learning (QML) has seen significant advancements, driven by recent improvements in Noisy Intermediate-Scale Quantum (NISQ) devices. Leveraging quantum principles such as entanglement and superposition, quantum convolutional neural networks (QCNNs) have demonstrated promising results in classifying both quantum and classical data. This study examines QCNNs in the context of image classification and proposes a novel strategy to enhance feature processing and a QCNN architecture for improved classification accuracy. First, a selective feature re-encoding strategy is proposed, which directs the quantum circuits to prioritize the most informative features, thereby effectively navigating the crucial regions of the Hilbert space to find the optimal solution space. Secondly, a novel parallel-mode QCNN architecture is designed to simultaneously incorporate features extracted by two classical methods, Principal Component Analysis (PCA) and Autoencoders, within a unified training scheme. The joint optimization involved in the training process allows the QCNN to benefit from complementary feature representations, enabling better mutual readjustment of model parameters. To assess these methodologies, comprehensive experiments have been performed using the widely used MNIST and Fashion MNIST datasets for binary classification tasks. Experimental findings reveal that the selective feature re-encoding method significantly improves the quantum circuit's feature processing capability and performance. Furthermore, the jointly optimized parallel QCNN architecture consistently outperforms the individual QCNN models and the traditional ensemble approach involving independent learning followed by decision fusion, confirming its superior accuracy and generalization capabilities. | N40: http://arxiv.org/abs/2507.02086v1
A41: 40 | B41: Hybrid Quantum-Classical Learning for Multiclass Image Classification | C41: Shuchismita Anwar and Sowmitra Das and Muhammad Iqbal Hossain and Jishnu Mahmud | E41: misc | G41: Exclude | H41: EC7 | K41: This study explores the challenge of improving multiclass image classification through quantum machine-learning techniques. It explores how the discarded qubit states of Noisy Intermediate-Scale Quantum (NISQ) quantum convolutional neural networks (QCNNs) can be leveraged alongside a classical classifier to improve classification performance. Current QCNNs discard qubit states after pooling; yet, unlike classical pooling, these qubits often remain entangled with the retained ones, meaning valuable correlated information is lost. We experiment with recycling this information and combining it with the conventional measurements from the retained qubits. Accordingly, we propose a hybrid quantum-classical architecture that couples a modified QCNN with fully connected classical layers. Two shallow fully connected (FC) heads separately process measurements from retained and discarded qubits, whose outputs are ensembled before a final classification layer. Joint optimisation with a classical cross-entropy loss allows both quantum and classical parameters to adapt coherently. The method outperforms comparable lightweight models on MNIST, Fashion-MNIST and OrganAMNIST. These results indicate that reusing discarded qubit information is a promising approach for future hybrid quantum-classical models and may extend to tasks beyond image classification. | N41: http://arxiv.org/abs/2508.18161v1
A42: 176 | B42: A novel qVGG-4 model for optimizing a parameterized quantum circuit in a quantum-IoT-based brain tumor detection and monitoring system | C42: Md Taimur Ahad and Bo Song and Yan Li | D42: Computer Methods and Programs in Biomedicine | E42: article | F42: 10.1016/j.cmpb.2026.109362 | G42: Include | H42: QCNN, HQCNN for Brain Tumor Detection | K42: Background Since brain tumors (BTs) require early detection for timely and effective treatment planning, this study presents two quantum deep learning (Q-DL) approaches: a quantum Convolutional Neural Network (CNN) and a quantum Vision Transformer (ViT). The implications of Q-DL for disease detection in medical images are limited, and previous studies have suggested that Q-DL has unsatisfactory accuracy. Methods To fill this gap, four models, (1) quantum CNN (Q-CNN), (2) hybrid quantum CNN (HQ-CNN), (3) Q-ViT, and (4) hybrid quantum ViT (HQ-ViT), were developed and tested on four BT-MRI datasets. BT patients demand real-time monitoring as they suffer from headaches, seizures, cognitive and behavioral changes, and neurological deficits. Therefore, we propose a smart brain tumor management system (SBTM) for real-time monitoring. Results Trained on the three brain tumor datasets using the Adam optimizer and five-fold cross-validation, the hybrid Q-DL, HQ-CNN, achieved an accuracy of 97%, and HQ-ViT achieved 96% in (tumor, no tumor) classification, which outperforms the parameterized quantum circuit (PQC)-based Q-DLs. The high accuracy of hybrid models continues: in 3 classes, 44% by CNN and 28% by HQ-ViT, and in 4 classes, 49% by HQ-CNN and 23% by HQ-ViT. The increased accuracy of hybrid models continues in the detection and classification test dataset of brain tumor MRI images. The results suggest that combining qVGG-4 with PQC in both CNNs and ViTs yields more powerful feature extraction than either alone. Conclusions The main novelty of this study is the use of a qVGG-4 model that optimizes PQC. Whereas traditional CNNs struggle with small tumors, the HQ-CNN and HQ-ViT methods achieve impressive accuracy even on 28 × 28-pixel images. This result solves the issue of handling complex lesion detection in small areas and accelerates the model training time. The high accuracy in detecting and classifying unseen MRI images is a significant contribution to SBTM. In clinical settings, a machine learning model is expected to perform well in detecting and classifying new MRI images. © 2026 The Author(s).
A43: 539 | B43: A Quantum CNN Approach for MRI Based Multi-Class Brain Tumor Classification | C43: Rajyalakshmi Pulicherla and Gireesh Namineni | D43: Proceedings - IEEE Madhya Pradesh Section Conference, MPCON 2026 | E43: inproceedings | F43: 10.1109/MPCON69668.2026.11508296 | G43: Include | H43: QCNN Approach for MRI Brain Tumor Classification & comparison | K43: The evolution of quantum computing has paved way for several evolutions, protruding into medical diagnosis too. This paper focuses on Quantum Convolutional Neural Network is compared with existing methods like Support Vector Machine, Convolutional Neural Network and ResNet18 used for brain tumor classification. A detailed study of various types of brain tumor is provided along with possible diagnosis and treatment. The frameworks corresponding to SVM, CNN, ResNet18 and QCNN are provided. The metrics used to evaluate the methods are provided like accuracy, precision, recall, F1 score, confusion matrix and quantum related metrics like Quantum Fidelity, Quantum Cross Entropy Loss, etc. The QCNN is observed to improved accuracy by 10.12%, precision by 10.96%, recall by 3.8%, specificity by 5.4%, F1 score by 7.1%, MSE by 65.5% good results in all parameters varying from 0.1% to 10.96% when compared with SVM, CNN and ResNet18, for multiclass brain tumor classification of Glioma, Meningioma, Pituitary and No Tumor. The quantum fidelity is about 1.0 and the quantum cross entropy is about 0.054. Hence QCNN proves to be a better choice for brain tumor classification. © 2026 IEEE.
A44: 215 | B44: A Quantum Convolutional Neural Network Approach for Early and Accurate Diagnosis of Parkinson’s Disease | C44: Aiesha Mahmoud Ibrahim and Mazin Abed Mohammed and Omar Al-Boridi | D44: Iraqi Journal for Computer Science and Mathematics | E44: article | F44: 10.52866/2788-7421.1288 | G44: Include | H44: QCNN for Parkinson's Diagnosis | I44: Exclude | J44: EC3 | K44: Parkinson’s disease (PD) is a progressive neurological disorder that primarily affects individuals over the age of 55. It is characterized by a range of motor and non-motor symptoms that can significantly impact various aspects of daily life. Despite notable advancements in medical science, there is currently no permanent cure or definitive treatment for PD. This therapeutic gap underscores the critical importance of early diagnosis, which remains a major focus of ongoing research. Due to the disease’s gradual progression, PD symptoms may take years to fully develop, making early detection essential for improving patient outcomes and quality of life. Moreover, the clinical presentation of PD overlaps with several other neurological conditions, highlighting the need for accurate and reliable diagnostic methods. This study proposes a novel framework for analyzing auditory data to enhance the precision of Parkinson’s disease diagnosis. By integrating quantum computing with neural network architectures, the proposed approach aims to improve diagnostic accuracy and support early detection and intervention. The quantum component facilitates more precise and efficient computations, while the neural model enhances information flow and feature extraction. Specifically, a Quantum Convolutional Neural Network (QCNN) is developed and evaluated using auditory data for PD diagnosis. The QCNN demonstrated exceptional performance on Dataset C, which includes 1,000 samples, achieving an accuracy of 99%, a precision of 99.5%, a recall of 99.5%, and an F1-score of 100%. Compared to classical convolutional neural networks, the proposed QCNN offers several advantages. Quantum algorithms are capable of performing specific computations significantly faster than their classical counterparts, leading to reduced processing time. Furthermore, they allow for a more compact representation of features, which lowers model complexity while enhancing overall performance and diagnostic accuracy. © 2025 The Author(s).
A45: 16 | B45: A Quantum Convolutional Neural Network Approach for Object Detection and Classification | C45: Gowri Namratha Meedinti and Kandukuri Sai Srirekha and Radhakrishnan Delhibabu | D45: APIN-D-23-03499/2023 | E45: article | G45: Maybe | H45: QCNN Analysis/Evaluation, check dataset and metrics | I45: Exclude | J45: EC7 | K45: This paper presents a comprehensive evaluation of the potential of Quantum Convolutional Neural Networks (QCNNs) in comparison to classical Convolutional Neural Networks (CNNs) and Artificial / Classical Neural Network (ANN) models. With the increasing amount of data, utilizing computing methods like CNN in real-time has become challenging. QCNNs overcome this challenge by utilizing qubits to represent data in a quantum environment and applying CNN structures to quantum computers. The time and accuracy of QCNNs are compared with classical CNNs and ANN models under different conditions such as batch size and input size. The maximum complexity level that QCNNs can handle in terms of these parameters is also investigated. The analysis shows that QCNNs have the potential to outperform both classical CNNs and ANN models in terms of accuracy and efficiency for certain applications, demonstrating their promise as a powerful tool in the field of machine learning. | N45: http://arxiv.org/abs/2307.08204v1
A46: 45 | B46: Towards Continuous-variable Quantum Neural Networks for Biomedical Imaging | C46: Daniel Alejandro Lopez and Oscar Montiel and Oscar Castillo and Miguel Lopez-Montiel | E46: misc | G46: Exclude | H46: EC4 | K46: Continuous-variable (CV) quantum computing offers a promising framework for scalable quantum machine learning, leveraging optical systems with infinite-dimensional Hilbert spaces. While discrete-variable (DV) quantum neural networks have shown remarkable progress in various computer vision tasks, CV quantum models remain comparatively underexplored. In this work, we present a feasibility study of continuous-variable quantum neural networks (CV-QCNNs) applied to biomedical image classification. Utilizing photonic circuit simulation frameworks, we construct CV quantum circuits composed of Gaussian gates, such as displacement, squeezing, rotation, and beamsplitters to emulate convolutional behavior. Our experiments are conducted on the MedMNIST dataset collection, a set of annotated medical image benchmarks for multiple diagnostic tasks. We evaluate CV-QCNN's performance in terms of classification accuracy, model expressiveness, and resilience to Gaussian noise, comparing against classical CNNs and equivalent DV quantum circuits. This study aims to identify trade-offs between DV and CV paradigms for quantum-enhanced medical imaging. Our results highlight the potential of continuous-variable models and their viability for future computer-aided diagnosis systems. | N46: http://arxiv.org/abs/2511.02051v1
A47: 404 | B47: A Quantum-Enhanced Deep Learning Framework for Precise Leaf Disease Detection in Tomato and Cotton Crops | C47: Nivethitha and Venkataramanan | D47: Iranian Journal of Science and Technology - Transactions of Electrical Engineering | E47: article | F47: 10.1007/s40998-025-00912-4 | G47: Include | H47: QCNN Variant used in a framework w/ metaheuristics for Leaf Disease Detection | I47: Exclude | J47: EC8 | K47: Leaf diseases significantly threaten agricultural yields, making their prompt and precise detection crucial for effective management and crop safeguarding. This work aims to create a strong classification framework for detecting leaf diseases in crops by utilizing advanced deep learning methods. The work uses the Dual-Tree Complex Wavelet Preprocessing Framework (DTCWPF) to standardize and reduce noise in input images by maintaining key features for accurate analysis. Feature extraction has been conducted using a blend of EfficientNet-B7 and Inception-ResNet v2 models for capturing a wide range of image attributes such as color, texture, shape, and structural details from both RGB and grayscale images. The Archimedes Optimization Algorithm (AOA) is then applied to select the most pertinent features and to enhance the classification performance.The framework integrates quantum computing principles by employing an Attention-Based Quantum Convolutional Neural Network (ABQCNN), coupled with Adaptive Silver Fox Algorithm (ASFA) for classification. This combination enhances the ability of the model to effectively prioritize salient data features and adaptively optimize feature selection, thereby improving the overall classification performance.To ensure the interpretability of the model predictions, GradCAM and GradCAM + + techniques are applied to generate class-discriminative visual explanations and for highlighting the critical regions within the leaf images those most significantly influence the classification outcomes. These visualization strategies provide valuable insights into the internal decision-making process of the model and subsequently, substantiate its robustness and reliability. The proposed framework has been evaluated on two tomato leaf datasets and two cotton leaf datasets and outstanding performances have been depicted. For the tomato leaf datasets, the model has achieved accuracies of 99.51% and 99.70%, respectively by demonstrating its robustness in classifying various tomato leaf diseases. Similarly, on the cotton leaf datasets, the model has achieved accuracies of 99.92% and 99.60%, respectively by demonstrating its effectiveness in distinguishing different cotton leaf conditions and highlighted the versatility of the framework as well as its potential application in real-world agricultural disease detection scenarios, thereby offering significant advancements in plant pathology. © The Author(s), under exclusive licence to Shiraz University 2025.
A48: 61 | B48: A Specialized Importance-Aware Quantum Convolutional Neural Network with Ring-Topology (IA-QCNN) for MGMT Promoter Methylation Prediction in Glioblastoma | C48: Emine Akpinar and Murat Oduncuoglu | E48: misc | G48: Include | H48: IA-QCNN on Medical/mpMPRI imaging | K48: GBM is a highly aggressive primary malignancy in adults, necessitating personalized therapeutic strategies due to its inherent molecular heterogeneity. MGMT promoter methylation is a pivotal prognostic biomarker for anticipating response to temozolomide-based chemotherapy. Although various AI frameworks have been developed for non-invasive MGMT prediction, spatial heterogeneity of methylation status and the high-dimensional and correlated nature of MRI data frequently constrain discriminative feature learning and generalizability of classical models. To circumvent these limitations, a specialized IA-QCNN architecture is proposed, based on the principles of quantum mechanics, including superposition and entanglement, and enabling more efficient representation learning in high-dimensional Hilbert space. The framework establishes a methodological bridge between GBM radiogenomics and quantum deep learning by integrating energy-based slice selection, importance-aware weighting, ring-topology quantum convolution, and folding-based pooling layers. When the model predicts MGMT promoter methylation status using both mpMRI and T1Gd images, experimental results demonstrate that the IA-QCNN achieves high accuracy despite its low number of trainable parameters while effectively minimizing the overfitting problem observed in classical models. Quantitative analyses reveal that the T1Gd modality possesses higher discriminative power than mpMRI, establishing a clinically significant sequence preference. Furthermore, the model exhibits exceptional robustness in hybrid noise environments, effectively utilizing noise as a regularization mechanism to enhance predictive performance. Consequently, the specialized IA-QCNN architecture provides a robust and computationally efficient alternative to classical approaches in the analysis of heterogeneous radiogenomic data. | N48: http://arxiv.org/abs/2604.22877v1
A49: 48 | B49: QuanvNeXt: An end-to-end quanvolutional neural network for EEG-based detection of major depressive disorder | C49: Nabil Anan Orka and Ehtashamul Haque and Maftahul Jannat and Md Abdul Awal and Mohammad Ali Moni | E49: misc | G49: Exclude | H49: EC4 | K49: This study presents QuanvNeXt, an end-to-end fully quanvolutional model for EEG-based depression diagnosis. QuanvNeXt incorporates a novel Cross Residual block, which reduces feature homogeneity and strengthens cross-feature relationships while retaining parameter efficiency. We evaluated QuanvNeXt on two open-source datasets, where it achieved an average accuracy of 93.1% and an average AUC-ROC of 97.2%, outperforming state-of-the-art baselines such as InceptionTime (91.7% accuracy, 95.9% AUC-ROC). An uncertainty analysis across Gaussian noise levels demonstrated well-calibrated predictions, with ECE scores remaining low (0.0436, Dataset 1) to moderate (0.1159, Dataset 2) even at the highest perturbation (ε = 0.1). Additionally, a post-hoc explainable AI analysis confirmed that QuanvNeXt effectively identifies and learns spectrotemporal patterns that distinguish between healthy controls and major depressive disorder. Overall, QuanvNeXt establishes an efficient and reliable approach for EEG-based depression diagnosis. | N49: http://arxiv.org/abs/2512.09517v1
A50: 44 | B50: Adapting Quantum Machine Learning for Energy Dissociation of Bonds | C50: Swathi Chandrasekhar and Shiva Raj Pokhrel and Navneet Singh | E50: misc | G50: Maybe | H50: EC6, same as 46 | K50: Accurate prediction of bond dissociation energies (BDEs) underpins mechanistic insight and the rational design of molecules and materials. We present a systematic, reproducible benchmark comparing quantum and classical machine learning models for BDE prediction using a chemically curated feature set encompassing atomic properties (atomic numbers, hybridization), bond characteristics (bond order, type), and local environmental descriptors. Our quantum framework, implemented in Qiskit Aer on six qubits, employs ZZFeatureMap encodings with variational ansatz (RealAmplitudes) across multiple architectures Variational Quantum Regressors (VQR), Quantum Support Vector Regressors (QSVR), Quantum Neural Networks (QNN), Quantum Convolutional Neural Networks (QCNN), and Quantum Random Forests (QRF). These are rigorously benchmarked against strong classical baselines, including Support Vector Regression (SVR), Random Forests (RF), and Multi-Layer Perceptrons (MLP). Comprehensive evaluation spanning absolute and relative error metrics, threshold accuracies, and error distributions shows that top-performing quantum models (QCNN, QRF) match the predictive accuracy and robustness of classical ensembles and deep networks, particularly within the chemically prevalent mid-range BDE regime. These findings establish a transparent baseline for quantum-enhanced molecular property prediction and outline a practical foundation for advancing quantum computational chemistry toward near chemical accuracy. | N50: http://arxiv.org/abs/2510.06563v1
A51: 50 | B51: Quanvolutional Neural Networks for Spectrum Peak-Finding | C51: Lukas Bischof and Rudolf M Füchslin and Kurt Stockinger and Pavel Sulimov | E51: misc | G51: Exclude | H51: EC4 | K51: The analysis of spectra, such as Nuclear Magnetic Resonance (NMR) spectra, for the comprehensive characterization of peaks is a challenging task for both experts and machines, especially with complex molecules. This process, also known as deconvolution, involves identifying and quantifying the peaks in the spectrum. Machine learning techniques have shown promising results in automating this process. With the advent of quantum computing, there is potential to further enhance these techniques. In this work, inspired by the success of classical Convolutional Neural Networks (CNNs), we explore the use of Quanvolutional Neural Networks (QuanvNNs) for the multi-task peak finding problem, involving both peak counting and position estimation. We implement a simple and interpretable QuanvNN architecture that can be directly compared to its classical CNN counterpart, and evaluate its performance on a synthetic NMR-inspired dataset. Our results demonstrate that QuanvNNs outperform classical CNNs on challenging spectra, achieving an 11\% improvement in F1 score and a 30\% reduction in mean absolute error for peak position estimation. Additionally, QuanvNNs appear to exhibit better convergence stability for harder problems. | N51: http://arxiv.org/abs/2512.13125v1
A52: 51 | B52: Practical Hybrid Quantum Language Models with Observable Readout on Real Hardware | C52: Stefan Balauca and Ada-Astrid Balauca and Adrian Iftene | E52: misc | G52: Exclude | H52: EC7 | K52: Hybrid quantum-classical models represent a crucial step toward leveraging near-term quantum devices for sequential data processing. We present Quantum Recurrent Neural Networks (QRNNs) and Quantum Convolutional Neural Networks (QCNNs) as hybrid quantum language models, reporting the first empirical demonstration of generative language modeling trained and evaluated end-to-end on real quantum hardware. Our architecture combines hardware-optimized parametric quantum circuits with a lightweight classical projection layer, utilizing a multi-sample SPSA strategy to efficiently train quantum parameters despite hardware noise. To characterize the capabilities of these models, we introduce a synthetic dataset designed to isolate syntactic dependencies in a controlled, low-resource environment. Experiments on IBM Quantum processors reveal the critical trade-offs between circuit depth and trainability, demonstrating that while noise remains a significant factor, observable-based readout enables the successful learning of sequential patterns on NISQ devices. These results establish a rigorous engineering baseline for generative quantum natural language processing, validating the feasibility of training complex sequence models on current quantum hardware. | N52: http://arxiv.org/abs/2512.12710v1
A53: 52 | B53: Quantifying Quanvolutional Neural Networks Robustness for Speech in Healthcare Applications | C53: Ha Tran and Bipasha Kashyap and Pubudu N Pathirana | E53: misc | G53: Exclude | H53: EC4 | K53: Speech-based machine learning systems are sensitive to noise, complicating reliable deployment in emotion recognition and voice pathology detection. We evaluate the robustness of a hybrid quantum machine learning model, quanvolutional neural networks (QNNs) against classical convolutional neural networks (CNNs) under four acoustic corruptions (Gaussian noise, pitch shift, temporal shift, and speed variation) in a clean-train/corrupted-test regime. Using AVFAD (voice pathology) and TESS (speech emotion), we compare three QNN models (Random, Basic, Strongly) to a simple CNN baseline (CNN-Base), ResNet-18 and VGG-16 using accuracy and corruption metrics (CE, mCE, RCE, RmCE), and analyze architectural factors (circuit complexity or depth, convergence) alongside per-emotion robustness. QNNs generally outperform the CNN-Base under pitch shift, temporal shift, and speed variation (up to 22% lower CE/RCE at severe temporal shift), while the CNN-Base remains more resilient to Gaussian noise. Among quantum circuits, QNN-Basic achieves the best overall robustness on AVFAD, and QNN-Random performs strongest on TESS. Emotion-wise, fear is most robust (80-90% accuracy under severe corruptions), neutral can collapse under strong Gaussian noise (5.5% accuracy), and happy is most vulnerable to pitch, temporal, and speed distortions. QNNs also converge up to six times faster than the CNN-Base. To our knowledge, this is a systematic study of QNN robustness for speech under common non-adversarial acoustic corruptions, indicating that shallow entangling quantum front-ends can improve noise resilience while sensitivity to additive noise remains a challenge. | N53: http://arxiv.org/abs/2601.02432v1
A54: 407 | B54: Advanced Optimized Quantum Learning for Robust Water Quality Assessment with an IoT Sensor Data | C54: Sakthivel Balu and Sheik Mohammed Abdul Raghabu and Ponnrajakumari Mahalingam and Jayaram Krishnasamy and Jeya Prakash Kadambarajan and Deivasigamani Subbramania Pattar | D54: Ingenierie des Systemes d'Information | E54: article | F54: 10.18280/isi.300207 | G54: Include | H54: QCNN w/ Metaheuristic for Water Quality Assessment | K54: In these decades smart transformation and the digital world are emerging with an effective enhancement. Meanwhile, the management of water quality has also become an important factor in ensuring public health and environmental sustainability. This work presents a real-time water quality prediction by integrating with an Internet of Things (IoT) based sensor data and an optimized quantum convolutional neural network (QCNN) method. The continuous update of water data namely pH, turbidity, dissolved oxygen, and temperature is collected from various sensors fitted inside water bodies. The dataset is gathered by using these sensors that are dynamically monitored using a QCNN method for efficient predictive accuracy and computation. Initially, the important features from the data are extracted using Modified Variational Autoencoder (M-VAE). The QCNN method works on a quantum computing principle that is suitable to handle complex, high-dimensional data. To improve accuracy in higher terms, the QCNN parameters are fine-tuned using a metaheuristic optimization. Therefore, the proposed algorithm of optimized QCNN ensures robustness and reliable performance of water quality in real-time. The validation results of the proposed methodology demonstrate prior deep learning models in terms of classification metrics. Finally, the proposed work satisfies the advancement in real-time water quality prediction and also contributes to a better solution for sustainable water resource management. ©2025 The authors.
A55: 278 | B55: Advanced speech emotion recognition utilizing optimized equivariant quantum convolutional neural network for accurate emotional state classification | C55: Balachandran G and Ranjith S and Jagan G C and Chenthil T R | D55: Knowledge-Based Systems | E55: article | F55: 10.1016/j.knosys.2025.113414 | G55: Include | H55: QCNN for Advanced SER w/ Metaheuristics | K55: Human-computer interaction frequently involves speech-emotion recognition (SER), which finds extensive use in domains like education, healthcare, and elder care. Researchers have to face difficulties in creating high-accuracy SER systems, even with advances in model identification and speech emotion feature extraction. To overcome these issues, in this manuscript Advanced SER utilizing an optimized Equivariant quantum convolutional neural network for Accurate Emotional State Classification (SER- EQCNN-ESC) was proposed. Initially, the input speech data is collected from the Ryerson Audio-Visual Database of Emotional Speech and Song (RAVDESS). The collected input data is then fed to pre-processing using Bellman filtering (BF) to remove noise and normalize the collected input data. Then the extracted features are fed to the Single Candidate Optimizer (SCO) to choose the best speech emotion characteristics. After that, the selected features are fed into the Equivariant Quantum Convolutional Neural Network (EQCNN) for SER and classified as Neutral, Happiness, Sadness, Anger, Fear, Disgust, Surprise, and calm. Generally, EQCNN does not express adapting optimization strategies to determine the finest parameters to ensure accurate recognition and classification of Speech emotion (SE). The performance of the proposed SER-EQCNN-ESC technique attains 18.80 %, 23.21 %, and 33.52 % higher accuracy, 19.41 %, 22.91 %, and 33.02 % higher precision contrasted with existing techniques like Automatic speech emotion detection using a hybrid of gray wolf optimizer and naïve Bayes (ASER-GWO[sbnd]NB), Modulation spectral features for speech emotion recognition using deep neural networks (SER-DNN) and A parallel-model speech emotion recognition network based on feature clustering (SER-FC-MDNN) models respectively. © 2025
A56: 195 | B56: Advancing neuroimaging with quantum convolutional neural networks for brain tumor detection | C56: Amrita Ticku and Vaibhav Sangwan and Sanket Balani and Sriti Jha and Sahil Rawat and Anu Rathee and Deepika Yadav | D56: International Journal of Information Technology (Singapore) | E56: article | F56: 10.1007/s41870-025-02401-7 | G56: Include | H56: QCNN for Brain Tumor Detection | I56: Exclude | J56: EC8 | K56: Brain tumor classification is crucial for effective patient care, but traditional MRI-based methods often face accuracy limitations, especially in distinguishing between tumor types. This study introduces a novel Quantum Convolutional Neural Network (QCNN) architecture that leverages quantum embedding, sparse input indexing, and four-qubit quantum convolution layers to enhance classification accuracy and efficiency. Developed using PennyLane and TensorFlow Quantum, our QCNN achieved a testing accuracy of 92.13% on a dataset of over 3000 MRI scans, matching the performance of the classical ResNet50 model while reducing training time from 64.95 s to just 1.1 s. These results suggest that QCNNs offer a promising new approach for improving brain tumor diagnostics, with the potential for faster and more accurate real-time medical applications, despite challenges in hardware limitations and model interpretability. © Bharati Vidyapeeth's Institute of Computer Applications and Management 2025.
A57: 130 | B57: Adversarial examples detection based on quantum fuzzy convolution neural network | C57: Chenyi Huang and Shibin Zhang | D57: Quantum Information Processing | E57: article | F57: 10.1007/s11128-024-04310-3 | G57: Maybe | H57: Uncertain? | I57: Exclude | J57: EC8 | K57: Combining the advantages of quantum computing and machine learning, quantum machine learning is anticipated to advance the field of artificial intelligence further. Recent research has demonstrated, however, that the state-of-the-art quantum classifiers can be deceived by adversarial examples, leading to incorrect classifications by quantum models. This paper proposes the quantum fuzzy convolutional neural network, which is used to detect adversarial examples, by combining the benefits of fuzzy systems and the quantum convolutional neural network. This defensive strategy does not modify the structure and training process of the quantum classifier that requires protection. Simulation experiments show that the adversarial example detection approach proposed in this paper can successfully separate the real data distribution from the adversarial data distribution and detect the adversarial examples generated by a specific attack method on a specific quantum classifier. © The Author(s), under exclusive licence to Springer Science+Business Media, LLC, part of Springer Nature 2024.
A58: 57 | B58: Beyond Barren Plateaus: A Scalable Quantum Convolutional Architecture for High-Fidelity Image Classification | C58: Radhakrishnan Delhibabu | E58: misc | G58: Exclude | H58: EC7 | K58: While Quantum Convolutional Neural Networks (QCNNs) offer a theoretical paradigm for quantum machine learning, their practical implementation is severely bottlenecked by barren plateaus -- the exponential vanishing of gradients -- and poor empirical accuracy compared to classical counterparts. In this work, we propose a novel QCNN architecture utilizing localized cost functions and a hardware-efficient tensor-network initialization strategy to provably mitigate barren plateaus. We evaluate our scalable QCNN on the MNIST dataset, demonstrating a significant performance leap. By resolving the gradient vanishing issue, our optimized QCNN achieves a classification accuracy of 98.7\%, a substantial improvement over the baseline QCNN accuracy of 52.32\% found in unmitigated models. Furthermore, we provide empirical evidence of a parameter-efficiency advantage, requiring $\mathcal{O}(\log N)$ fewer trainable parameters than equivalent classical CNNs to achieve $>95\%$ convergence. This work bridges the gap between theoretical quantum utility and practical application, providing a scalable framework for quantum computer vision tasks without succumbing to loss landscape concentration. | N58: http://arxiv.org/abs/2603.11131v1
A59: 54 | B59: AI-Driven Cardiorespiratory Signal Processing: Separation, Clustering, and Anomaly Detection | C59: Yasaman Torabi | E59: misc | G59: Include | H59: QCNN used for Cardiorespiratory signal processing | K59: This research applies artificial intelligence (AI) to separate, cluster, and analyze cardiorespiratory sounds. We recorded a new dataset (HLS-CMDS) and developed several AI models, including generative AI methods based on large language models (LLMs) for guided separation, explainable AI (XAI) techniques to interpret latent representations, variational autoencoders (VAEs) for waveform separation, a chemistry-inspired non-negative matrix factorization (NMF) algorithm for clustering, and a quantum convolutional neural network (QCNN) designed to detect abnormal physiological patterns. The performance of these AI models depends on the quality of the recorded signals. Therefore, this thesis also reviews the biosensing technologies used to capture biomedical data. It summarizes developments in microelectromechanical systems (MEMS) acoustic sensors and quantum biosensors, such as quantum dots and nitrogen-vacancy centers. It further outlines the transition from electronic integrated circuits (EICs) to photonic integrated circuits (PICs) and early progress toward integrated quantum photonics (IQP) for chip-based biosensing. Together, these studies show how AI and next-generation sensors can support more intelligent diagnostic systems for future healthcare. | N59: http://arxiv.org/abs/2602.09210v1
A60: 59 | B60: Pixel-Translation-Equivariant Quantum Convolutional Neural Networks via Fourier Multiplexers | C60: Dmitry Chirkov and Igor Lobanov | E60: misc | G60: Exclude | H60: EC5 | K60: Convolutional neural networks owe much of their success to hard-coding translation equivariance. Quantum convolutional neural networks (QCNNs) have been proposed as near-term quantum analogues, but the relevant notion of translation depends on the data encoding. For address/amplitude encodings such as FRQI, a pixel shift acts as modular addition on an index register, whereas many MERA-inspired QCNNs are equivariant only under cyclic permutations of physical qubits. We formalize this mismatch and construct QCNN layers that commute exactly with the pixel cyclic shift (PCS) symmetry induced by the encoding. Our main technical result is a constructive characterization of all PCS-equivariant unitaries: conjugation by the quantum Fourier transform (QFT) diagonalizes translations, so any PCS-equivariant layer is a Fourier-mode multiplexer followed by an inverse QFT (IQFT). Building on this characterization, we introduce a deep PCS-QCNN with measurement-induced pooling, deferred conditioning, and inter-layer QFT cancellation. We also analyze trainability at random initialization and prove a lower bound on the expected squared gradient norm that remains constant in a depth-scaling regime, ruling out a depth-induced barren plateau in that sense. | N60: http://arxiv.org/abs/2604.06094v2
A61: 60 | B61: QShield: Securing Neural Networks Against Adversarial Attacks using Quantum Circuits | C61: Navid Azimi and Aditya Prakash and Yao Wang and Li Xiong | E61: misc | G61: Exclude | H61: EC4 | K61: Deep neural networks remain highly vulnerable to adversarial perturbations, limiting their reliability in security- and safety-critical applications. To address this challenge, we introduce QShield, a modular hybrid quantum-classical neural network (HQCNN) architecture designed to enhance the adversarial robustness of classical deep learning models. QShield integrates a conventional convolutional neural network (CNN) backbone for feature extraction with a quantum processing module that encodes the extracted features into quantum states, applies structured entanglement operations under realistic noise models, and outputs a hybrid prediction through a dynamically weighted fusion mechanism implemented via a lightweight multilayer perceptron (MLP). We systematically evaluate both classical and hybrid quantum-classical models on the MNIST, OrganAMNIST, and CIFAR-10 datasets, using a comprehensive set of robustness, efficiency, and computational performance metrics. Our results demonstrate that classical models are highly vulnerable to adversarial attacks, whereas the proposed hybrid models with entanglement patterns maintain high predictive accuracy while substantially reducing attack success rates across a wide range of adversarial attacks. Furthermore, the proposed hybrid architecture significantly increased the computational cost required to generate adversarial examples, thereby introducing an additional layer of defense. These findings indicate that the proposed modular hybrid architecture achieves a practical balance between predictive accuracy and adversarial robustness, positioning it as a promising approach for secure and reliable machine learning in sensitive and safety-critical applications. | N61: http://arxiv.org/abs/2604.10933v1
A62: 92 | B62: ALS Detection Framework Based on Automatic Singular Spectrum Analysis and Quantum Convolutional Neural Network From EMG Signals | C62: K K Makam and V K Singh and R B Pachori | D62: IEEE Sensors Letters | E62: article | F62: 10.1109/LSENS.2024.3449369 | G62: Include | H62: QCNN for ALS Detection | K62: Electromyogram (EMG) signals are recordings of the electrical activity in muscles, which are studied due to their informative nature regarding neuromuscular disorders. Analysis of EMG signals is invaluable for identifying various neuromuscular conditions. In this letter, an automatic singular spectrum analysis (Auto-SSA) and quantum convolutional neural network (QCNN)-based framework is proposed for the detection of amyotrophic lateral sclerosis (ALS) using EMG signals. The Auto-SSA effectively decomposes the EMG signals into reconstructed components, from which the particle swarm optimization extracts the most significant features. The QCNN classifies the extracted features for efficient ALS detection. The proposed framework outperforms the compared state-of-the-art ALS detection frameworks, achieving a testing accuracy of 98.50%. With the obtained performance, the proposed framework could be a valuable diagnostic tool for ALS neuromuscular conditions.
A63: 62 | B63: Do We Really Need Quantum Machine Learning?: A Multidimensional Empirical Study | C63: Sudip Vhaduri and Ryan Gammon and Sayanton Dibbo | E63: misc | G63: Exclude | H63: EC6 | K63: The rapid growth of computer vision and increasingly complex image recognition tasks has exposed fundamental computational limitations of classical machine learning models, motivating the exploration of quantum computing as an emerging new paradigm. This paper presents a comprehensive benchmarking study of classical and quantum machine learning models for image recognition on the MNIST handwritten digit dataset, evaluating both traditional models, a Classical Support Vector Machine (CSVM) and a Quantum Support Vector Machine (QSVM), and deep neural network models, a Classical Convolutional Neural Network (CCNN) and a Quantum Convolutional Neural Network (QCNN), across four performance dimensions: classification accuracy, computational runtime, parameter count, and memory requirements. Experiments are conducted as functions of both feature dimensionality and sample size, and across CPU and GPU execution environments, providing a controlled, multidimensional comparison to address gaps in prior work. For the SVM-based models, QSVM consistently outperforms CSVM in accuracy, reaching $\sim$ 0.90 versus $\sim$ 0.85 at 1,000 samples, with a higher computational cost. A feature count of 10 qubits and a sample size in the range of 200 -- 500 emerge as practical operating points that balance accuracy and runtime. For the neural network models, CCNN and QCNN achieve comparable classification accuracy, both exceeding 0.96 at 64 features and 60,000 samples, yet QCNN offers substantially superior parameter and memory efficiency, requiring $\sim$ 94\% fewer parameters and $\sim$ 75\% less memory than CCNN at higher feature counts, while incurring higher runtime. Across both model families, quantum models consistently outperform classical models by greater margins in accuracy as feature dimensionality or sample size increases. | N63: http://arxiv.org/abs/2605.27923v1
A64: 63 | B64: Quantum Machine Learning for Industrial Applications | C64: Léo Monbroussou | D64: Sorbonne University, EDITE doctoral school, LIP6 laboratory, 2025 | E64: article | F64: 10.70675/78b65d31z6c74z4ccfz8ce3zdbde6bf748e9 | G64: Exclude | H64: EC5 | K64: Recent advances in Machine Learning have transformed numerous industrial sectors, yet classical paradigms face fundamental limitations: rapidly growing data volumes, rising computational costs, significant energy consumption, and the physical scaling limits of conventional hardware architectures. Quantum computing has emerged as a promising computational paradigm to address these challenges, giving rise to the field of Quantum Machine Learning (QML). In this thesis, the theoretical foundations of QML are investigated, with a focus on near-term and future practical applications. Three central challenges are addressed: the trainability of variational quantum circuits, their expressivity, and their resistance to efficient classical simulation. The trainability of Hamming-weight preserving variational quantum circuits is first studied, and theoretical guarantees are established that resolve an open conjecture on the absence of barren plateaus for this circuit family. Subspace-preserving QML algorithms are then introduced, including photonic circuits and quantum convolutional neural networks, and are designed to mimic classical ML subroutines while offering polynomial quantum advantage. Finally, variational quantum circuits are analyzed as quantum Fourier models, and a framework is derived to jointly characterize expressivity and trainability, from which conditions are obtained under which quantum models provably separate from their classical counterparts. These contributions are intended to advance the theoretical roadmap for harnessing near-term and future quantum technologies in real-world applications. | N64: http://arxiv.org/abs/2606.14822v1
A65: 64 | B65: High-Speed Train Brake Pads Condition Monitoring Based on Trade-Off Contrastive Learning Network | C65: M Zhang and J Li and J Mo and M Shen and Z Xiang and Z Zhou | D65: IEEE Transactions on Instrumentation and Measurement | E65: article | F65: 10.1109/TIM.2024.3485406 | G65: Exclude | H65: EC4 | K65: The braking system of high-speed trains is directly related to the operation safety of the train. The brake pads, which play a crucial role, will inevitably undergo uneven wear in long-term use, posing safety hazards to train braking. As the trains are in normal operating condition for long periods, it is difficult to collect usable uneven wear data, and there is a situation of data imbalance. This article proposes a trade-off contrastive learning network (TCLN), utilizing the differences between data and balancing the weights of different classes, which can realize the condition monitoring under the data imbalance of brake pads. First, data augmentation is employed to provide sufficient and diverse data for contrastive learning, and nonlinear features are extracted by a quadratic convolutional neural network (QCNN). Then, the designed class-weighted method is utilized to improve the characterization ability of the minority class data and realize the equidistant representation of features for each class, which in turn achieves the purpose of paying equal attention to all classes. Finally, the effectiveness of the proposed method is verified using the dataset collected from the scaling experiments, and the results show that the proposed method has higher accuracy and efficiency compared to other methods, which can still accurately identify the brake pad condition when the data are highly imbalanced.
A66: 65 | B66: Attention-Embedded Quadratic Network (Qttention) for Effective and Interpretable Bearing Fault Diagnosis | C66: J -X. Liao and H -C. Dong and Z -Q. Sun and J Sun and S Zhang and F -L. Fan | D66: IEEE Transactions on Instrumentation and Measurement | E66: article | F66: 10.1109/TIM.2023.3259031 | G66: Exclude | H66: EC4 | K66: Bearing fault diagnosis is of great importance to decrease the damage risk of rotating machines and further improve economic profits. Recently, machine learning, represented by deep learning, has made great progress in bearing fault diagnosis. However, applying deep learning to such a task still faces major challenges such as effectiveness and interpretability: 1) when bearing signals are highly corrupted by noise, the performance of deep learning models drops dramatically and 2) a deep network is notoriously a black box. It is difficult to know how a model classifies faulty signals from the normal and the physics principle behind the classification. To solve these issues, first, we prototype a convolutional network with recently invented quadratic neurons. This quadratic neuron-empowered network can qualify the noisy bearing data due to the strong feature representation ability of quadratic neurons. Moreover, we independently derive the attention mechanism from a quadratic neuron, referred to as qttention, by factorizing the learned quadratic function in analog to the attention, making the model made of quadratic neurons inherently interpretable. Experiments on the public and our datasets demonstrate that the proposed network can facilitate effective and interpretable bearing fault diagnosis. Our code is available at https://github.com/asdvfghg/QCNN_for_bearing_diagnosis.
A67: 66 | B67: A Comparative Study of Quantum-Classical Approaches in Neural Network Architectures for Medical Imaging Applications | C67: V K B and M Rajasekaran | D67: 2026 International Conference on Recent Advancement in Electrical, Computer and Communication Technologies (IECCT) | E67: article | F67: 10.1109/IECCT68664.2026.11541603 | G67: Exclude | H67: EC3 | K67: Quantum circuits and classical convolutional neural networks are used in hybrid quantum-classical neural networks (HQCNNs) to classify medical images, particularly MRI and CT scans for bone cancer diagnosis. This review covers cutting-edge hybrid designs for parallel quantum circuit tumour detection, illness diagnosis, and anatomical pattern identification. Recent research reveal methodological trends, performance benchmarks, and architectural advances that improve classification accuracy, computing efficiency, and parameter optimisation by quantum. On medical imaging datasets like musculoskeletal imaging, parallel quantum computing architectures train 12 times quicker while keeping accuracy. Quantum hardware limits, noise resilience, scalability restrictions, and model interpretability are discussed in relation to clinical bone cancer screening implementation. Quantum transfer learning, federated quantum machine learning, and orthopaedic imaging-optimized hardware-aware quantum circuit design are future directions.
A68: 108 | B68: Amplitude transformed quantum convolutional neural network | C68: Shiqin Di and Jinchen Xu and Guoqiang Shu and Congcong Feng and Xiaodong Ding and Zheng Shan | D68: Applied Intelligence | E68: article | F68: 10.1007/s10489-023-04581-w | G68: Include | H68: QCNN Variant | I68: Exclude | J68: EC8 | K68: With the rapid development of quantum neural networks (QNN), several quantum simulations of convolutional neural networks (CNN) have been proposed. Among them, Google has proposed three quantum convolutional neural network (QCNN) models, but its purely QCNN model suffers from slow convergence and low training efficiency. In this work, we design low-depth parameterized quantum circuits with only two quantum bits interacting and construct a QCNN framework with lower depths, fewer parameters and global correlation. Based on this, we propose an Amplitude Transformed Quantum Convolutional Neural Network (ATQCNN). Experiments show that our model achieves 100% and 97.92% accuracy and faster convergence on the quantum cluster state and CICMalDroid2020 datasets compared to the purely QCNN proposed by Google. In particular, the required parameters and depth of ATQCNN are in reduced by about 27% for the same scale of qubits. It will be more suitable for current noisy intermediate-scale quantum (NISQ) devices. © 2023, The Author(s), under exclusive licence to Springer Science+Business Media, LLC, part of Springer Nature.
A69: 68 | B69: Quaternion Convolutional Neural Network With EMAP Representation for Multisource Remote-Sensing Data Classification | C69: Y -L. Wei and Y -B. Zheng and R Wang and H -C. Li | D69: IEEE Geoscience and Remote Sensing Letters | E69: article | F69: 10.1109/LGRS.2023.3310572 | G69: Exclude | H69: EC4 | K69: The fusion and classification of hyperspectral images (HSIs) and light detection and ranging (LiDAR) data have been extensively studied using deep learning. However, traditional real-valued deep-learning methods have limitations in distinguishing internal and external relations and capturing fine spatial characteristics. To break through these limitations, this letter proposes a quaternion convolutional neural network (QCNN) with extended morphological attribute profile (EMAP) quaternion representation (called EQR) for multisource remote-sensing (RS) data classification by utilizing quaternion properties. Specifically, we first propose the EQR for each single-source data, which encodes the multiattribute features in a compact, yet comprehensive manner, highlighting the internal relations. Second, we embed EQR into QCNN to preserve the internal relations and enable the interaction of multiattribute features. Then, we develop the 3-D quaternion convolution (3DQConv) to better exploit the 3-D characteristic of HSIs. Finally, we design different attention mechanisms and a two-level fusion strategy for multisource data to learn enhanced features. Experiments on two multisource RS datasets show that the proposed method achieved better performance than other state-of-the-art classification methods.
A70: 454 | B70: An enhanced classification framework based on quantum resonance dimensionality reduction and hybrid quantum ensemble learning | C70: Gaojie Wu and Yumin Dong | D70: International Journal of Modern Physics C | E70: article | F70: 10.1142/S0129183126430084 | G70: Maybe | H70: Check application domain/datasets and use case | I70: Exclude | J70: EC8 | K70: With the rapid growth of data volume and complexity, traditional machine learning algorithms encounter significant challenges in handling large-scale and high-dimensional datasets. To address these limitations, this paper proposes an enhanced classification framework based on Quantum Resonance Dimensionality Reduction (QRDR) and Hybrid Quantum Ensemble Learning (HQEL). First, a Multi-Kernel Quantum Support Vector Machine (MKQSVM) is introduced, which integrates the advantages of multiple quantum kernel functions and employs Bayesian optimization to automatically determine the optimal kernel combination. This approach enhances the model’s adaptability and generalization ability on heterogeneous data. Second, the hybrid quantum ensemble learning model combines MKQSVM and Quantum Convolutional Neural Network (QCNN) through a stacking ensemble strategy with a classical meta-learner, thereby achieving improved prediction accuracy and stability. Moreover, the proposed QRDR algorithm is utilized to reduce the dimensionality of high-dimensional data while retaining critical features and minimizing redundancy, which effectively improves both training efficiency and predictive performance of the quantum models. Experimental results demonstrate that the proposed method outperforms traditional machine learning approaches on multiple benchmark datasets, particularly in classifying complex and high-dimensional data. © 2026 World Scientific Publishing Company.
A71: 70 | B71: Quantum Computing in Transportation Engineering: A Survey | C71: S Somvanshi and S Das and M M Islam and S B B Polock and G Chhetri and D Anderson | D71: IEEE Transactions on Intelligent Transportation Systems | E71: article | F71: 10.1109/TITS.2026.3662626 | G71: Exclude | H71: EC3 | K71: Quantum computing introduces powerful computational paradigms capable of addressing optimization and machine learning challenges that are increasingly critical in transportation engineering. This paper presents a comprehensive survey of how quantum algorithms and models are being applied across transportation domains, including intelligent transportation systems, traffic management, vehicle routing, logistics, and autonomous systems. Unlike prior reviews that primarily introduce quantum theory, we systematically connect fundamental quantum principles-qubits, superposition, entanglement, and quantum gates-with specific transportation use cases. We synthesize recent findings showing that the Quantum Approximate Optimization Algorithm, Grover's search, and hybrid quantum–classical solvers can improve performance in combinatorial problems such as vehicle routing and dynamic traffic signal control, while quantum machine learning models (e.g., Quantum Convolutional Neural Networks, Quantum Generative Adversarial Networks, and clustering algorithms) demonstrate promise in traffic prediction, anomaly detection, and autonomous vehicle perception. Our review highlights that although quantum hardware limitations (noise, scalability, connectivity) remain significant, empirical studies already suggest measurable improvements in solution quality and computational efficiency when compared to classical heuristics. The key contribution of this survey is to map the landscape of quantum computing in transportation engineering, identify application-specific advantages and current bottlenecks, and outline future research directions toward scalable, domain-specific quantum algorithms. By doing so, we provide transportation researchers and practitioners with a structured foundation to integrate quantum approaches into emerging mobility systems, with implications for efficiency, safety, sustainability, and equity.
A72: 71 | B72: Quantum Machine Learning in Medical Image Analysis: From Diagnostics to Surgery Planning | C72: A Sar and A Kumar and S Roy and A Kaushish and T Choudhury and Minakshi and S S Alqahtani and A Abraham | D72: IEEE Access | E72: article | F72: 10.1109/ACCESS.2026.3663498 | G72: Exclude | H72: EC3 | K72: Quantum Machine Learning (QML) is an emerging, powerful paradigm at the intersection of quantum computing and artificial intelligence, with the potential to enhance medical image analysis. We compared their performance with classical counterparts, while critically examining the gap between theoretical quantum advantages and the practical constraints of current Noisy Intermediate-Scale Quantum (NISQ) implementations. This review explored the current landscape of QML-based methodologies applied to key medical imaging modalities - Magnetic Resonance Imaging (MRI), Computed Tomography (CT), X-rays, and histopathology. We systematically analyzed how quantum-enhanced models were employed for critical tasks such as image classification, segmentation, and reconstruction, and we compared their performance with that of classical counterparts. The review delved into the architectural innovations that enabled these quantum approaches, including hybrid quantum-classical frameworks, variational quantum circuits, and quantum convolutional neural networks. Particular emphasis was given to the clinical relevance of QML applications, from early diagnostics to real-time surgery planning, and how quantum advantage might influence data efficiency, interpretability, along computational scalability. Finally, we highlighted current challenges in data encoding, noise resilience, and hardware limitations, and discussed promising future directions that could enable the practical deployment of QML in healthcare settings. This comprehensive review aimed to serve as a foundational reference for researchers and practitioners looking to harness quantum computing in medical imaging and precision medicine.
A73: 72 | B73: Enriching Earth Observation Labeled Data With Quantum Conditioned Diffusion Models | C73: F Mauro and F De Falco and L Papa and A Ceschini and A Sebastianelli and P Gamba and M Panella and S L Ullo | D73: IEEE Transactions on Geoscience and Remote Sensing | E73: article | F73: 10.1109/TGRS.2026.3661445 | G73: Exclude | H73: EC4 | K73: The rapid adoption of diffusion models (DMs) in the Earth observation (EO) domain has unlocked new generative capabilities aimed at producing new samples, whose statistical properties closely match real imagery, for tasks such as synthesizing missing data, augmenting scarce labeled datasets, and improving image reconstruction. This is particularly relevant in EO, where labeled data are often costly to obtain and limited in availability. However, classical DMs still face significant computational limitations, requiring hundreds to thousands of inference steps, as well as difficulties in capturing the intricate spatial and spectral correlations characteristic of EO data. Recent research in quantum machine learning (QML), including initial attempts of quantum generative models, offers a fundamentally different approach to overcoming these challenges. Motivated by these considerations, we introduce the quanvolutional conditioned U-Net (QCU-Net), a hybrid quantum–classical architecture that applies quantum operations within a conditioned diffusion framework using a novel quanvolutional feature-extraction approach, for generating synthetic labeled EO imagery. Extensive experiments on the EuroSAT RGB dataset demonstrate that our QCU-Net achieves superior results. Notably, it reduces the Fréchet inception distance by 64%, lowers the Kernel inception distance by 76%, and yields higher semantic accuracy. Ablation studies further reveal that strategically positioning quantum layers and employing entangling variational circuits enhance model performance and convergence. This work represents the first successful adaptation of class-conditioned quantum diffusion modeling in the EO domain, paving the way for quantum-enhanced remote sensing imagery synthesis.
A74: 73 | B74: Quantum Approaches for Dysphonia Assessment in Small Speech Datasets | C74: H Tran and B Kashyap and P N Pathirana | D74: 2025 47th Annual International Conference of the IEEE Engineering in Medicine and Biology Society (EMBC) | E74: article | F74: 10.1109/EMBC58623.2025.11252849 | G74: Exclude | H74: EC4 | K74: Dysphonia, a prevalent medical condition, leads to voice loss, hoarseness, or speech interruptions. To assess it, researchers have been investigating various machine learning techniques alongside traditional medical assessments. Convolutional Neural Networks (CNNs) have gained popularity for their success in audio classification and speech recognition. However, the limited availability of speech data, poses a challenge for CNNs. This study compares the performance of CNNs with standard convolutional layers, CNNs with random nonlinear convolutional layers (RANDOM models), and a novel hybrid quantum-classical architecture, Quanvolutional Neural Networks (QNNs), which are well-suited for small datasets. The audio data was preprocessed into Mel spectrograms, comprising 243 training samples and 61 testing samples in total, and used in four experiments. A total of six models were developed: two CNNs, two RANDOM models, and two QNNs, with the second models incorporating additional layers to boost performance. The angle encoding method was employed within the quanvolutional layer, which is the quantum transformation layer of the QNNs, to enable the representation of more complex features of Mel spectrogram. The experimental results demonstrated that QNN models consistently outperformed the CNN models in both classification accuracy (ranging from 82.22% ± 4% to 89.26% ± 2%) and convergence speed across all four experiments.Clinical relevance— This work investigates the potential of quantum-based approaches for medical data classification and their promising role in enhancing dysphonia assessment.
A75: 74 | B75: Detecting Double Mixed Compressed Images Based on Quaternion Convolutional Neural Network | C75: H Wang and J Wang and X Hu and B Hu and Q Yin and X Luo and B Ma and J Sun | D75: Chinese Journal of Electronics | E75: article | F75: 10.23919/cje.2022.00.179 | G75: Exclude | H75: EC4 | K75: Detection of color images that have undergone double compression is a critical aspect of digital image forensics. Despite the existence of various methods capable of detecting double Joint Photographic Experts Group (JPEG) compression, they are unable to address the issue of mixed double compression resulting from the use of different compression standards. In particular, the implementation of Joint Photographic Experts Group 2000 (JPEG2000) as the secondary compression standard can result in a decline or complete loss of performance in existing methods. To tackle this challenge of JPEG+JPEG2000 compression, a detection method based on quaternion convolutional neural networks (QCNN) is proposed. The QCNN processes the data as a quaternion, transforming the components of a traditional convolutional neural network (CNN) into a quaternion representation. The relationships between the color channels of the image are preserved, and the utilization of color information is optimized. Additionally, the method includes a feature conversion module that converts the extracted features into quaternion statistical features, thereby amplifying the evidence of double compression. Experimental results indicate that the proposed QCNN-based method improves, on average, by 27% compared to existing methods in the detection of JPEG+JPEG2000 compression.
A76: 240 | B76: An Evaluation of FRQI and NEQR Encoding Using QCNN for Forecasting Tropical Cyclone Intensity | C76: Rajamohana and Vani Yelamali and K. Sakthi Mahendran and Ritik Jain and Karthiganesh Durai | D76: Computacion y Sistemas | E76: article | F76: 10.13053/cys-29-3-5448 | G76: Include | H76: QCNN using FRQI/NEQR for Cycle Intensity Detection | K76: Effective weather forecasting for cyclones is crucial for minimizing harm to both people and the environment. Accurate estimation of tropical cyclone (TC) intensity is essential for disaster prevention. Although convolutional neural networks (CNNs) have improved this process, they often struggle to capture global spatial relationships in images. Quantum Image Processing (QIP) leverages quantum computing advantages but faces challenges such as noise and hardware limitations. This study represents the first effort to estimate tropical cyclone intensity prediction using two popular quantum image representation formats: Flexible Representation of Quantum Images (FRQI) and a Novel Enhanced Quantum Representation (NEQR), as data encoders in Quantum Convolutional Neural Networks (QCNN) utilizing INSAT 3D satellite images. By employing TCs from 2012 to 2021 as training data, the model achieved an overall mean square error (MSE) of 0.0384 for FRQI and 0.0002 for NEQR. The findings indicate that NEQR significantly outperforms FRQI in cyclone image prediction. © 2025, Instituto Politecnico Nacional. All rights reserved.
A77: 520 | B77: An Exploratory Statistical Analysis of South Korean Nurse Migration Determinants from Aggregated Data | C77: Seong-Heui Kim | D77: International Journal for Global Academic and Scientific Research | E77: article | F77: 10.55938/ijgasr.v5i2.414 | G77: Include | H77: Verify QCNN centrality | K77: The home country of South Korean nurses has a shortage of career opportunities and salaries. Acclimatising to the new cultural and work environments in foreign countries may not be easy. Balancing work, family life, with the plan of moving to a new place is an additional challenge. To resolve these problems, this research suggests that the Multi-Head Probsparse Fast Quantum Convolutional Neural Network and Doll Maker Optimization (MHPFQCNN-DMO) can effectively and efficiently predict international nurse migration. Initially, data is acquired from the dataset “South Korean Cities Nurse Migration Synthetic 600.csv,” which includes Region, Gender, Push Factor, and Percentage attributes. The method employed to preprocess the data is the Adjusted Min-Max with Decimal Scaling and Statistical Column Normalization (AMMDS-SCN), which takes care of the missing data, codes the categorical variables, and normalizes the data to ensure the seamless training of the model. The Tactical Unit Pine Cone Optimization (TUPCO) algorithm is then applied in selecting relevant features to balance exploration and exploitation to maintain the most meaningful features. The Multi-Head Probsparse Fast Quantum Convolutional Neural Network (MHPFQCNN) predicts nurse migration tendencies by analyzing region, gender, push factor, and percentage. Finally, the Doll Maker Optimization (DMO) algorithm optimises the network weights, improving accuracy, minimizing false predictions, and improving computational efficiency. ©The Author 2026 and 2026 by Seong-Heui Kim.
A78: 77 | B78: Learning Quaternion Convolutional Neural Networks for PolSAR Target Recognition | C78: H Lin and J Yin and J Yang | D78: IEEE Transactions on Aerospace and Electronic Systems | E78: article | F78: 10.1109/TAES.2025.3645163 | G78: Exclude | H78: EC4 | K78: Polarization offers rich information for enhancing target recognition in synthetic aperture radar (SAR) imagery. However, most existing SAR target recognition methods rely on single-channel data, and the potential of multichannel polarimetric images remains underexplored. In this article, we propose an end-to-end target recognition framework for polarimetric SAR (PolSAR) images based on a quaternion convolutional neural network (QCNN) operating in the Poincaré sphere parameter domain. The QCNN is constructed with a sequence of quaternion operation layers and incorporates a specialized loss function designed for quaternion-valued representations. To address the mismatch problem in the quaternion field, we introduce quaternion maximum pooling and quaternion average pooling operations. To the best of our knowledge, this is the first QCNN developed for PolSAR target recognition. Experiments on both simulated and real datasets demonstrate that the proposed QCNN achieves recognition performance comparable to state-of-the-art real- and complex-valued models while requiring significantly fewer parameters and offering enhanced physical interpretability, thereby validating the effectiveness and superiority of the proposed approach.
A79: 78 | B79: Quadruplet Convolution Neural Network With C3 Loss (C3-QCNN) for Signal Classification | C79: C Yang and S Yang and Z Feng and M Wang | D79: IEEE Transactions on Instrumentation and Measurement | E79: article | F79: 10.1109/TIM.2022.3217846 | G79: Exclude | H79: EC4 | K79: In this article, a new quadruplet convolution neural network (QCNN) is proposed to cooperatively and contrastively learn deep features of raw radio signals for accurate automatic modulation classification (AMC) when very few labeled samples are available. Four convolutional channels with shared weights are constructed to deal with the in-phase ( $I$ ) path and quadrature ( $Q$ ) path of signals. Moreover, a new cooperative–contrastive–classification (C3)-loss function that contains the cooperative loss, contrastive loss, and classification loss is designed for QCNN to extract discriminative and concise features of signals. Some experiments are taken on the public dataset generated with GNU Radio, which has 11 types of modulation signals with different signal-to-noise ratios. The experimental results show that the QCNN with C3 loss (C3-QCNN) achieves high classification accuracy and outperform its counterparts.
A80: 306 | B80: An inception-ResNet deep learning approach to classify tumours in the ovary as benign and malignant | C80: Ashwini Kodipalli and Srirupa Guha and Santosh Dasar and Taha Ismail | D80: Expert Systems | E80: article | F80: 10.1111/exsy.13215 | G80: Include | H80: QCNN used, but main focus is Inception-ResNet v2 (check in stage 2) | K80: The classification of tumours into benign and malignant continues to date to be a very relevant and significant research topic in the cancer research domain. With the advent of Computer Vision and rapid developments in the fields of deep learning, as well as medical devices and instruments, researchers are therefore utilizing the state-of-the-art deep learning architectures to discover patterns in the medical image data and thereby use this information to detect tumours and classify them as benign or malignant. In this paper, we propose a custom state-of-the-art deep learning architecture, the Inception-ResNet v2 for the classification of ovarian tumours into the two categories of benign and malignant based on a custom dataset with a validation accuracy of 97.5% and a test accuracy of 67%. Furthermore, a quantum convolutional neural network (QCNN) was also implemented with an accuracy of 92% on the validation dataset. © 2022 John Wiley & Sons Ltd.
A81: 80 | B81: Recent Developments in Quantum Machine Learning | C81: I Kahvazadeh and A C Fong | D81: 2025 International Conference on Intelligent \& Innovative Practices in Engineering \& Management (IIPEM) | E81: article | F81: 10.1109/IIPEM65914.2025.11547992 | G81: Exclude | H81: EC6 | K81: Motivated by the anticipated advantage of quantum computing in complex tasks, quantum machine learning (QML) combines quantum principles with machine learning (ML) for potential speedups. This paper reviews recent progress in three main directions: (a) Variational Quantum Algorithms (VQAs), (b) Quantum Convolutional Neural Networks (QCNNs), and (c) quantum kernel methods. Key challenges are highlighted, including data encoding, hardware noise in the Noisy Intermediate-Scale Quantum (NISQ) regime, and the importance of standardized benchmarking. Promising strategies to address these challenges include hybrid quantum-classical integration, transfer learning, and algorithm-hardware co-design. Experimental demonstrations on platforms developed by IBM, Google, and IonQ illustrate the feasibility of QML on near-term quantum devices. Looking forward, advances in encoding schemes, noise-resilient circuit design, and domain-specific applications in chemistry, materials, and biomedicine are expected to further accelerate the practical development of QML.
A82: 81 | B82: Quaternion Convolutional Neural Networks: Enhancing Color Image Classification through Inter-Channel Relationships | C82: A Sharma and A Kumar | D82: 2026 International Conference on Intelligent Computing, Networks, and Security (IC-ICNS) | E82: article | F82: 10.1109/IC-ICNS68863.2026.11537942 | G82: Exclude | H82: EC4 | K82: A key challenge in color image classification is the efficient representation of Red, Green and Blue channels while preserving the inherent inter channel relationships. Traditional Convolutional Neural Networks(CNNs) treat each channel independantly. Quaternion Convolutional Neural Networks(QCNNs) address this limitation by extending the real valued neural network framework into a four-dimensional space. In this work, we propose a Quaternion Convolutional Neural Network architecture that leverages quaternion convolution to facilitate interactions between all channels of the input and filter simultaneously using the Hamilton product. A weight initialization strategy to ensure convergence during training is adopted for the quaternion framework. The proposed model is evaluated against an equivalent real-valued CNN counterpart on the image classification task using CIFAR-10 dataset. Experimental findings indicate that the proposed QCNN achieves comparable classification accuracy while requiring approximately four times fewer trainable parameters.
... A90: 196 | B90: Application of image recognition algorithm based on quantum convolutional neural network | C90: Xueyang Zhao | D90: 2025 IEEE 5th International Conference on Electronic Technology, Communication and Information, ICETCI 2025 | E90: inproceedings | F90: 10.1109/ICETCI64844.2025.11084236 | G90: Maybe | H90: Check if the QCNN is still a functional QCNN | K90: In this paper, an innovative Quantum image recognition algorithm, Quantum Auto Gradient Descent (QAGD), is proposed. The algorithm combines the advantages of quantum convolutional neural networks (QCNN), autoencoders (AE) and low-lot gradient descent (MGD). The introduction of an automatic encoder into the quantum convolutional neural network can effectively extract image features and reduce dimensionality, reduce data dimensions while retaining key information, and improve the model's ability to capture image features. At the same time, combined with the small-batch gradient descent optimization strategy, the model parameters are iteratively updated through small-batch data, which speeds up the model convergence speed and improves the training efficiency. In the experimental part, we compare QAGD with traditional image recognition algorithms, and the results show that QAGD algorithm has significant advantages in improving image recognition performance and reducing false positive rate, with higher recognition accuracy and faster training speed. This fully verifies the feasibility and effectiveness of QAGD architecture in the application of image recognition algorithms based on quantum convolutional neural networks. © 2025 IEEE.
A91: 41 | B91: Application of Quantum Convolutional Neural Networks for MRI-Based Brain Tumor Detection and Classification | C91: Sugih Pratama Nugraha and Ariiq Islam Alfajri and Tony Sumaryada and Duong Thanh Tai and Nissren Tamam and Abdelmoneim Sulieman and Sitti Yani | E91: misc | G91: Include | H91: QCNN for Brain Tumor Classification | K91: This study explores the application of Quantum Convolutional Neural Networks (QCNNs) for brain tumor classification using MRI images, leveraging quantum computing for enhanced computational efficiency. A dataset of 3,264 MRI images, including glioma, meningioma, pituitary tumors, and non-tumor cases, was utilized. The data was split into 80% training and 20% testing, with an oversampling technique applied to address class imbalance. The QCNN model consists of quantum convolution layers, flatten layers, and dense layers, with a filter size of 2, depth of 4, and 4 qubits, trained over 10 epochs. Two models were developed: a binary classification model distinguishing tumor presence and a multiclass classification model categorizing tumor types. The binary model achieved 88% accuracy, improving to 89% after data balancing, while the multiclass model achieved 52% accuracy, increasing to 62% after oversampling. Despite strong binary classification performance, the multiclass model faced challenges due to dataset complexity and quantum circuit limitations. These findings suggest that QCNNs hold promise for medical imaging applications, particularly in binary classification. However, further refinements, including optimized quantum circuit architectures and hybrid classical-quantum approaches, are necessary to enhance multiclass classification accuracy and improve QCNN applicability in clinical settings. | N91: http://arxiv.org/abs/2509.02582v1
A92: 358 | B92: Artificial Intelligence (AI) Enabled Vehicle Detection and counting Using Deep Learning | C92: Mohana and Rahul Kejriwal and Ritika and Arpit Arora | D92: 2022 International Conference on Computer Communication and Informatics, ICCCI 2022 | E92: inproceedings | F92: 10.1109/ICCCI54379.2022.9740929 | G92: Include | H92: QCNN-LSTM for Model Training for Vehicle Detection | K92: Urban traffic management is the system for assessing and controlling density of vehicles on road, to avoid traffic congestion. Vehicle counting is an important module it aids in traffic prediction and urban infrastructure planning. In this paper, various Artificial Intelligence tools and their applications for vehicle detection and counting have been analysed and elaborated. For vehicle detection, used deep learning based YOLOv3 algorithm a highly efficient and accurate algorithm for detecting different classes of vehicles. The role of edge-devices, which locally process the data that they are fed with. Application of Big Data and different AI tools like GNN, LSTM, and QCNN was described for vehicle detection and counting. AI is used to predict and detect traffic flow. Big data helps in maintaining an efficient traffic management system. Both combined, contribute in developing a systematic traffic management system. The objective behind using LSTM networks is to prevent the long term dependency problem. QCNN is used for efficient model training. Organizations implementing vehicle counting and detection focus more on the concise sensors and in house development of efficient algorithms in order to have extensive research and development. © 2022 IEEE.
A93: 412 | B93: Automatic classification of pancreatic cancer from urinary biomarkers using equivariant quantum convolutional neural networks with hybrid optimization algorithm | C93: Vivekanandan G and Soma Prathibha and Suganthi P and Sankaranarayanan R and Nallarasan V and Ravikumar Sethuraman | D93: Computer Methods in Biomechanics and Biomedical Engineering | E93: article | F93: 10.1080/10255842.2025.2575873 | G93: Include | H93: QCNN Variant w/ Metaheuristic for Pancreatic Cancer Detection | I93: Exclude | J93: EC8 | K93: Early detection of Pancreatic Ductal Adenocarcinoma (PDAC) is crucial to improve survival rates. This study proposes an automated classification framework using equivariant quantum convolutional neural networks (EQCNNs) optimized with a Hybrid Adam-Dingo and Quantum Artificial Hummingbird Algorithm (HybADOQAHA). Urinary biomarkers–creatinine, lymphatic vessel endothelial hyaluronan receptor 1 (LYVE1), regenerating islet-derived protein 1 beta (REG1B), and trefoil factor 1(TFF1) were analyzed from 590 samples comprising healthy, benign, and PDAC cases. Pre-processing with dual-feature filtering and feature extraction via lifted Euler characteristic transform enhanced data quality. The experimental results demonstrate better accuracy, precision, recall, specificity, and Area Under the Curve (AUC) compared with baseline models, establishing the proposed method as a promising non-invasive diagnostic tool for early PDAC detection. © 2025 Informa UK Limited, trading as Taylor & Francis Group.
A94: 320 | B94: Benchmarking Quantum Convolutional Neural Networks for Signal Classification in Simulated Gamma-Ray Burst Detection | C94: Farida Farsian and Nicolo Parmiggiani and Alessandro Rizzo and Gabriele Panebianco and Andrea Bulgarelli and Francesco Schilliro and Carlo Burigana and Vincenzo Cardone and Luca Cappelli and Massimo Meneghetti and Giuseppe Murante and Giuseppe Sarracino and Roberto Scaramella and Vincenzo Testa and Tiziana Trombetti | D94: Proceedings - 33rd Euromicro International Conference on Parallel, Distributed, and Network-Based Processing, PDP 2025 | E94: inproceedings | F94: 10.1109/PDP66500.2025.00059 | G94: Include | H94: QCNN for identifying signals resembling Gamma-Ray Bursts | K94: This study evaluates the use of Quantum Convolutional Neural Networks (QCNNs) for identifying signals resembling Gamma-Ray Bursts (GRBs) within simulated astrophysical datasets in the form of light curves. The task addressed here focuses on distinguishing GRB-like signals from background noise in simulated Cherenkov Telescope Array Observatory (CTAO) data, the next-generation astrophysical observatory for very high-energy gamma-ray science. QCNNs, a quantum counterpart of classical Convolutional Neural Networks (CNNs), leverage quantum principles to process and analyze high-dimensional data efficiently. We implemented a hybrid quantum-classical machine learning technique using the Qiskit framework, with the QCNNs trained on a quantum simulator. Several QCNN architectures were tested, employing different encoding methods such as Data Reuploading and Amplitude encoding. Key findings include that QCNNs achieved accuracy comparable to classical CNNs, often surpassing 90%, while using fewer parameters, potentially leading to more efficient models in terms of computational resources. A benchmark study further examined how hyperparameters like the number of qubits and encoding methods affected performance, with more qubits and advanced encoding methods generally enhancing accuracy but increasing complexity. QCNNs showed robust performance on time-series datasets, successfully detecting GRB signals with high precision. The research is a pioneering effort in applying QCNNs to astrophysics, offering insights into their potential and limitations. This work sets the stage for future investigations to fully realize the advantages of QCNNs in astrophysical data analysis. © 2025 IEEE.
A95: 531 | B95: Bone Cancer Detection in X-Ray Images Using Latent Equivariant Quantum Convolutional Networks with Atomic Orbital Search Optimization | C95: Soubraylu Sivakumar and Krishna Prakash Arunachalam and Elangovan and Ratna Kumari Tamma | D95: International Journal of Image and Graphics | E95: article | F95: 10.1142/S0219467827500951 | G95: Include | H95: QCNN Variant for Bone Cancer Detection | I95: Exclude | J95: EC8 | K95: Bone cancer is a life-threatening disease in which early and accurate detection plays a vital role in reducing mortality and preventing the spread of malignant cells. To address this challenge, this study proposes a novel Latent Equivariant Quantum Convolutional Neural Network with Atomic Orbital Search (LEQCNN-AOS) for enhanced bone cancer detection from X-ray images. Initially, bone X-ray images are collected from the TCIA dataset and preprocessed using the Dual Bilateral Least Squares Hybrid Filter (DBLSF), which effectively suppresses noise while preserving critical edge and structural details associated with cancerous regions. Quantum K-Means Clustering (QK-MC) is then employed for image segmentation, where image features are encoded into quantum states and swap tests are utilized to accurately cluster suspicious areas. For feature extraction, the Kolmogorov–Arnold Transformer (KAT) is introduced, combining Kolmogorov–Arnold Networks with Vision Transformers to capture complex tissue patterns through residual connections and logical activation functions. Finally, Atomic Orbital Search (AOS) optimizes LEQCNN hyperparameters by simulating electron energy transitions, ensuring an effective balance between exploration and exploitation. Experimental results demonstrate superior performance on the TCIA dataset, achieving 99.85% accuracy, 99.68% precision, and a 99.72% F-score, highlighting the robustness, interpretability, and clinical potential of the proposed framework. © 2027 World Scientific Publishing Company.
A96: 457 | B96: Brain Tumor Detection Using Quantum Convolution Neural Networks | C96: Karvi Pranay Kumar and Aryan Mahawar and Kunal Singh and Tarryn Reiner D Silva and Tapan Batla and Natarajan | D96: 2026 2nd International Conference on Intelligent Systems for Communication, IoT and Security, ICISCoIS 2026 | E96: inproceedings | F96: 10.1109/ICISCoIS62701.2026.11447931 | G96: Include | H96: QCNN/HQCNN for Brain Tumor Detection | K96: Brain Tumor detection knows as tedious job poses huge intricacies. Though MRI(Magnetic Resonance Imaging) has made the life of clinicians easier by providing detailed cross-sections of the brain, thus making it easy to detect abnormalities, it is still very difficult to accurately categorize the different types of Brain Tumors. For addressing this problem, this research work proposes a novel approach to use a Hybrid Quantum Classical Convolutional Neural Network (HQC-CNN) model. The proposed model has been experimented on the BraTS2023 dataset, with a result of 98.7% accuracy, which is an improvement of 5.2% over traditional CNNs (ResNet, VGG). The HQC-CNN model simplifies parameter complexity by 40% and training time by 2.5 times via quantum parallelism. The complete flow is described in the architecture, hybrid training regimes, and issues in deploying QCNNs on near-term quantum hardware in this work. These findings strongly indicates the power of Deep Learning approaches and incorporation of Quantum ideas in medical imaging. © 2026 IEEE.
A97: 357 | B97: Brain Tumour Detection Using Quantum Convolutional Neural Networks (QCNN) | C97: Karthik and Snehanvitha and Addanki Sai Kumar and Dattatreya Teella and R Naga Shreya and Shalini Ramanathan | D97: OCIT 2025 - Proceedings 23rd OITS International Conference on Information Technology | E97: inproceedings | F97: 10.1109/OCIT66168.2025.11400476 | G97: Include | H97: QCNN for Brain Tumor Detection | K97: Brain tumor detection is a vital and challenging task in medical diagnosis, requiring highly precise and efficient methods to improve patient treatment outcomes. Traditional approaches rely on classical machine learning and deep learning techniques, which, while effective to a degree, often struggle with capturing the complex and high-dimensional patterns present in medical imaging data. A significant limitation of these conventional methods is their inability to process and analyze intricate features efficiently, which can impact diagnostic accuracy. To address these challenges, this work proposes a novel Quantum Convolutional Neural Network (QCNN) framework that combines quantum computing principles, via quantum circuits, with classical machine learning architectures implemented through tools like PyTorch and PennyLane. This hybrid approach enhances feature extraction and classification capabilities, leading to superior performance. Experimental results demonstrate that the QCNN model achieves an improved accuracy of 90 percent on the test dataset, surpassing traditional methods and showing promise for advancing brain tumor detection technology. This improvement is supported by consistent decreases in training and validation loss during model training, highlighting the robustness and efficacy of the quantum-enhanced model. © 2025 IEEE.
A98: 97 | B98: Rotation equivariant quantum graph neural networks with trainable compression encoder and entanglement-enhanced aggregation | C98: Wenjie Liu and Bohan Du and Weiwei Liu and Yifan Zhu | D98: Neural Networks | E98: article | F98: 10.1016/j.neunet.2026.108625 | G98: Exclude | H98: EC4 | K98: The integration of symmetry, such as permutation equivariance, into Quantum Graph Neural Networks (QGNNs), referred to as Equivariant Quantum Graph Neural Networks (EQGNNs), markedly improves the model's generalization performance on graph-structured data. Despite this advancement, current research has not yet extended rotational equivariance to QGNN frameworks. Furthermore, processing large-scale graph data increases computational complexity due to numerous inter-node connections, significantly raising the required number of qubits. To address these challenges, a novel Rotationally Equivariant Quantum Graph Neural Network (REQGNN) with trainable compression encoder and entanglement-enhanced aggregation mechanism is proposed. By adopting quantum fidelity as the evaluation metric, we design a quantum autoencoder to effectively compress feature dimensionality, substantially lowering the qubit requirements of the model while preserving essential global structural details. To achieve rotational equivariance in the model, we propose an entanglement-enhanced layer that incorporates distance and angle information between nodes. This layer performs entanglement by extracting diverse edge information, thereby further refining edge feature extraction. Additionally, an auxiliary entanglement layer is introduced to mitigate the over-smoothing issue. Experimental results demonstrate REQGNN is significantly better for graph classification tasks than GIN, Gra+QSVM, and Gra+QCNN on four datasets in all metrics and achieves better results than egoGQNN in accuracy on PTC dataset, and it also has advantage for graph regression tasks over the classical models, including EGNN and EquiformerV2, and reduces the MAE of Cv task unit by 20% on average compared with a previous quantum model QGCNN. Our approach offers an effective solution for achieving rotational equivariance while providing a novel perspective for exploring symmetry in graph neural networks (GNNs). © 2026 The Author(s)
A99: 98 | B99: CNN Convolutional layer optimisation based on quantum evolutionary algorithm | C99: Tzyy-Chyang Lu | D99: Connection Science | E99: article | F99: 10.1080/09540091.2020.1841111 | G99: Exclude | H99: EC7 | K99: In this paper, a quantum convolutional neural network (CNN) architecture is proposed to find the optimal number of convolutional layers. Since quantum bits use probability to represent binary information, the quantum CNN does not represent the actual network, but the probability of existence of each convolutional layer, thus achieving the aim of training weights and optimising the number of convolutional layers at the same time. In the simulation part, CIFAR-10 (including 50k training images and 10k test images in 10 classes) is used to train VGG-19 and 20-layer, 32-layer, 44-layer and 56-layer CNN networks, and compare the difference between the optimal and non-optimal convolutional layer networks. The simulation results show that without optimisation, the accuracy of the test data drops from approximately 90% to about 80% as the number of network layers increases to 56 layers. However, the CNN with optimisation made it possible to maintain the test accuracy at more than 90%, and the number of network parameters could be reduced by nearly half or more. This shows that the proposed method can not only improve the network performance degradation caused by too many hidden convolutional layers, but also greatly reduce the use of the network’s computing resources. © 2020 Informa UK Limited, trading as Taylor & Francis Group.
A100: 131 | B100: Breast Cancer Severity Classification; Mesh Denoising Graph Triple Attention with Stereoscopic Scalable Quantum Convolutional Neural Networks | C100: Indhumathi and S. Rukmani Devi and Asma and Kalpana and Sandhiya and Denis | D100: 2025 6th International Conference on Data Intelligence and Cognitive Informatics, ICDICI 2025 | E100: inproceedings | F100: 10.1109/ICDICI66477.2025.11135114 | G100: Include | H100: QCNN Variant for BC using MIAS | K100: Breast cancer diagnosis and classification are often hindered by challenges such as low image quality, overlapping tissue features, and the lack of distinct tumor boundaries. These limitations contribute to high false-negative and false-positive rates, reducing diagnostic accuracy. Additionally, the scarcity of annotated data and the computational complexity of existing models further impact their performance. To address these issues, advanced imaging techniques, improved feature extraction, and robust classification strategies are essential. This study presents and validates the Mesh Denoising Graph Triple Attention with Stereoscopic Scalable Quantum Convolutional Neural Networks (MD-GTA-SSQCNNet) for breast cancer severity classification using the MIAS (Mammographic Image Analysis Society) dataset. The process begins with Adaptive Mesh Denoising Guided Normal Filtering (AMDGNF), which enhances image quality. This is followed by segmentation of tumor-affected regions using the Geometric Algebra Transformer (GAT). Feature extraction and classification are carried out using the Graph Triple Attention with Stereoscopic Scalable Quantum Convolutional Neural Network (GTASSQCNNet). To further improve classification accuracy across multiple breast cancer classes, the Osprey Optimization Algorithm (OsOA) is employed; optimizing the model based on tumor class distribution and affected regions. The Pythonbased implementation using the MIAS dataset demonstrates that MD-GTA-SSQCNNet significantly outperforms conventional approaches, achieving 99.9% classification efficiency and 99.8 % sensitivity. These results highlight the potential for highly accurate automated systems to assist or even replace manual diagnosis in breast cancer detection. © 2025 IEEE.
A101: 100 | B101: Securing Health Records Using Quantum Convolutional Neural Network | C101: Arulmozhi and Sheeba and Pradeep Devaneyan | D101: Lecture Notes in Networks and Systems | E101: book | F101: 10.1007/978-981-19-7874-6_53 | G101: Exclude | H101: EC3 | K101: In block chain technology, a distributed architecture, blocks are the data storage and processing unit. Data must be exchanged from one party to another safely and securely, and the block chain must be updated using smart contracts. But still, the problem facing was securing the healthcare data. So, this paper proposed securing health records using the QCNN method, which stands for a Quantum Convolutional Neural Network with Block Chain Technology, to safeguard medical data. Block chain technology's consensus process ensures that all data is correct and all transactions are safe. The datasets are collected from the data world repository. The datasets are pre-processed using label coding with the standard scalar method. The features are analyzed with QCNN and the patient healthcare data to increase the security and interoperability using block chain technology. The research specifically looks at Electronic Health Record (EHR) security issues to be overcome. This proposed quantum conventional neural network (QCNN) deep learning architecture provides higher accuracy and security than the other existing algorithms. © 2023, The Author(s), under exclusive license to Springer Nature Singapore Pte Ltd.
A102: 101 | B102: QEA-QCNN: optimization of quantum convolutional neural network architecture based on quantum evolution | C102: Yangyang Li and Xiaobin Hao and Guanlong Liu and Ronghua Shang and Licheng Jiao | D102: Memetic Computing | E102: article | F102: 10.1007/s12293-024-00417-3 | G102: Exclude | H102: EC5 | K102: Quantum neural network (QNN) is a research orientation that combines quantum computing and machine learning. It has the potential to solve the bottleneck problem of shortage of computing resource in deep learning, and is expected to become the first practical application scheme that demonstrate application level quantum advantages on current Noise Intermediate scale Quantum (NISQ) devices. However, limited by the current scale of NISQ devices, QNNs have fewer quantum bits and quantum circuits cannot be too deep. Currently, there is no clear design strategy for the architecture of QNN. Designing QNN architectures arbitrarily not only has high circuit complexity but also often poor network performance. Similar to classical convolutional neural network, in this paper, a quantum evolution-based optimization algorithm is proposed for design of quantum convolutional neural network (QCNN) architecture. The design of QNN architecture is viewed as a combinatorial optimization problem, and the quantum evolution algorithm is used to adaptively design the QCNN architecture with its global search ability in a large discrete search space. Comprehensive experimental results indicate that the proposed method can effectively reduce the complexity of QCNN circuits, reduce the difficulty of deploying quantum circuits, and further improve the expressibility of QCNN. © The Author(s), under exclusive licence to Springer-Verlag GmbH Germany, part of Springer Nature 2024.
A103: 280 | B103: Change map of flood detection using attention mechanism assisted quantum convolutional neural network utilising SAR and optical images | C103: Ankita Dixit and Indu Chawla | D103: International Journal of Image and Data Fusion | E103: article | F103: 10.1080/19479832.2026.2613394 | G103: Include | H103: QCNN variants for generating flood change maps using pre/post images | I103: Exclude | J103: EC8 | K103: Climate change has intensified the frequency of extreme weather events, with floods posing a significant threat to environmental, economic, and societal stability. Accurate and timely flood detection is therefore essential for effective disaster response. By leveraging the complementary strengths of Sentinel-1 SAR (all-weather capability) and Sentinel-2 optical imagery (high spatial resolution), two quantum-assisted attention-based models, SA-QCNN and CA-QCNN, are proposed for generating flood change maps using pre- and post-event images. SA-QCNN computes attention within a single modality, while CA-QCNN enhances cross-domain feature fusion by using SAR features as keys, optical features as queries and values. Experiments on the Ombria flood dataset demonstrate that CA-QCNN achieves 96.88% overall accuracy and 91.2% F1-score, surpassing SA-QCNN’s 92.1% accuracy and 86.12% F1-score. These results confirm the advantages of quantum-assisted attention mechanisms for integrating multimodal satellite data, highlighting the robustness of CA-QCNN in capturing cross-domain features and underscoring the potential of quantum computing to advance flood detection in remote sensing. © 2026 Informa UK Limited, trading as Taylor & Francis Group.
A104: 103 | B104: Automatic English-Speaking Fluency Scoring System Based on Automatic Speech Assessment | C104: Hua Wang and Jun Zhang | D104: Circuits, Systems, and Signal Processing | E104: article | F104: 10.1007/s00034-025-03429-7 | G104: Exclude | H104: EC6 | K104: With the increasing requirement for language learning and evaluation tools, it is necessary to develop an automated speech assessment system. However, the existing systems rarely deliver a clear score for speech fluency and pronunciation, which is lower than human perception. The goal of this research is to develop an Automatic English-Speaking Fluency Scoring System (AESFSS) to assess the fluency of English speakers using multiple speech variables. This approach utilizes deep learning (DL) models and a multidimensional approach to extract critical speech parameters, including speech rate, pause duration, pitch change, and pronunciation accuracy. The dataset comprises voices in the English language, recorded from various speakers. These samples vary in speaking styles, pronunciation, and fluency levels. Data preprocessing uses the Wiener Filter to reduce noise and feature extraction by Mel-frequency Cepstral Coefficients (MFCCs) for measuring the spectral properties of speech. A scoring algorithm with a dynamic chimp optimized efficient Elman neural network (DCO-EENN) is used to return fluency scores based on features retrieved. The results show that AESFSS is highly accurate, with 95% accuracy. The DCO-EENN model attained 0.95 of precision, 0.948 of Recall, and 0.949 of F1-score, which are superior to other spoken English evaluation models.Baseline metrics such as DeepProsody (Yang et al. in Lee, Decentralizing Feature Extraction with Quantum Convolutional Neural Network for Automatic Speech Recognition, 2021), BP Model (Yeung et al. in Alzheimers Res Ther. 10.1186/s13195-021-00848-x, 2021), SVM (Zhang et al. in Circuits Syst Signal Process 41(12):6827–6843, 2022), TDNN (Zhang et al. in Circuits Syst Signal Process 41(12):6827–6843, 2022), and HDE (Zou et al. in System 126, 103497, 2024) are reported from their respective original researches. These models were compared with CMU ARCTIC dataset to better evaluate the performance. This approach realistically captures not only the rhythm but also the natural flow in speech, making the instrument trustworthy for assessing fluency automatically. © The Author(s), under exclusive licence to Springer Science+Business Media, LLC, part of Springer Nature 2025.
A105: 252 | B105: Comparison of CNN and QCNN Performance in Binary Classification of Breast Cancer Histopathological Images | C105: Taieba Tasnim and Mohammad Rahman and Fan Wu | D105: Proceedings - 2024 IEEE International Conference on Big Data, BigData 2024 | E105: inproceedings | F105: 10.1109/BigData62323.2024.10825102 | G105: Include | H105: QCNN for Breast Cancer Detection | K105: Breast cancer is a leading cause of mortality among women, with early detection being crucial for improving outcomes. This study explores the use of Quantum Convolutional Neural Network (QCNN) for automating breast cancer detection through histopathological images. We compare QCNNs with classical Convolutional Neural Network (CNN) for binary classification of benign and malignant tumors using the BreakHis dataset. Our results demonstrate that QCNN outperform CNN in accuracy, especially in smaller batch sizes, and offer faster convergence with improved computational efficiency. This highlights QCNNs' potential in enhancing diagnostic precision and efficiency in medical imaging. © 2024 IEEE.
A106: 105 | B106: QCNN-H: Single-Image Dehazing Using Quaternion Neural Networks | C106: Vladimir Frants and Sos Agaian and Karen Panetta | D106: IEEE Transactions on Cybernetics | E106: article | F106: 10.1109/TCYB.2023.3238640 | G106: Exclude | H106: EC4 | K106: Single-image haze removal is challenging due to its ill-posed nature. The breadth of real-world scenarios makes it difficult to find an optimal dehazing approach that works well for various applications. This article addresses this challenge by utilizing a novel robust quaternion neural network architecture for single-image dehazing applications. The architecture's performance to dehaze images and its impact on real applications, such as object detection, is presented. The proposed single-image dehazing network is based on an encoder-decoder architecture capable of taking advantage of quaternion image representation without interrupting the quaternion dataflow end-to-end. We achieve this by introducing a novel quaternion pixel-wise loss function and quaternion instance normalization layer. The performance of the proposed QCNN-H quaternion framework is evaluated on two synthetic datasets, two real-world datasets, and one real-world task-oriented benchmark. Extensive experiments confirm that the QCNN-H outperforms state-of-the-art haze removal procedures in visual quality and quantitative metrics. Furthermore, the evaluation shows increased accuracy and recall of state-of-the-art object detection in hazy scenes using the presented QCNN-H method. This is the first time the quaternion convolutional network has been applied to the haze removal task. © 2013 IEEE.
A107: 106 | B107: HM-QCNN: Hybrid Multi-branches Quantum-Classical Neural Network for Image Classification | C107: Haowen Liu and Yufei Gao and Lei Shi and Lin Wei and Zheng Shan and Bo Zhao | D107: Lecture Notes in Computer Science (including subseries Lecture Notes in Artificial Intelligence and Lecture Notes in Bioinformatics) | E107: book | F107: 10.1007/978-3-031-46664-9_10 | G107: Exclude | H107: EC3 | K107: Quantum machine learning has been developing in recent years, demonstrating great potential in various research domains and promising applications for pattern recognition. However, due to the constraints of quantum hardware, the input qubits are restricted caused by small circuit size, and the fuzziness in all dimensions caused by the features that are difficult to be effectively mined. Besides, previous studies focus on binary classification, but multi-classification received little attention. To address the difficulty in multi-classification, this paper proposed a hybrid multi-branches quantum-classical neural network (HM-QCNN) that utilizes a multi-branch strategy to construct the convolutional part. The part consists of three branches to extract the features of different scales and morphologies. Two quantum convolutional layers apply quantum CRZ gates and rotational gates to design a random quantum circuit (RQC) with 4 qubits and full qubits measurements. The experiments on three public datasets (MNIST, Fashion MNIST, and MedMNIST) demonstrate that HM-QCNN outperforms other prevalent methods with accuracy, precision, and convergence speed. Compared with the classical CNN and the hybrid neural network without multi-branches, HM-QCNN reached 97.40% and improved the accuracy of classification by 6.45% and 1.36% on the MNIST dataset, respectively. © 2023, The Author(s), under exclusive license to Springer Nature Switzerland AG.
...

Sheet Criteria
A1: Inclusion (ALL must hold)
A2: IC1 | B2: Publications between January 1st 2021- June 20th 2026
A3: IC2 | B3: Publications must be in English
A4: IC3 | B4: Limited to Conference Papers, Articles, Journal Articles & Relevant Preprints.
A5: IC4 | B5: Articles implementing or applying QCNNs, HQCNNs for practical use cases.
A6: IC5 | B6: Works demonstrating practical application of QCNN or HQCNN technology with documented results and accuracy readings.
A8: Exclusion (ANY excludes; record code)
A9: EC1 | B9: Excluding all papers that aren’t English
A10: EC2 | B10: Publications before January 1st 2021 and after June 20th 2026.
A11: EC3 | B11: Articles without full text, extended abstracts, duplicates, or reviews, editorials & books.
A12: EC4 | B12: Studies that do not directly incorporate QCNN/HQCNN models
A13: EC5 | B13: Studies that are primarily theoretical or conceptual papers that do not involve the application of a model to a problem task
A14: EC6 | B14: Studies where the proposed QCNN/HQCNN model mentions aren’t the paper’s own contribution, mentioned from related works or are peripheral mentions.
A15: EC7 | B15: Studies that use only synthetic datasets and do not demonstrate applicability to a domain-specific problem.
A16: EC8 | B16: Studies that are not accessible via the available institutional access provided by the host university.
